{
    "odata.metadata": "https://app.legco.gov.hk/VRDB/odata/$metadata#vVotingResult",
    "odata.count": "56",
    "value": [
        {
            "id": 47797,
            "start_date": "2012-11-07T00:00:00",
            "type": "Council Meeting",
            "term_no": 5,
            "vote_number": 2,
            "vote_date": "2012-11-07T00:00:00",
            "vote_time": "2012-11-07T17:42:53",
            "motion_ch": "鍾國斌議員對何秀蘭議員的「同志平權」議案作出的修正案",
            "motion_en": "AMENDMENT BY HON CHUNG KWOK-PAN TO HON CYD HO'S MOTION ON \"EQUAL RIGHTS FOR PEOPLE OF DIFFERENT SEXUAL ORIENTATIONS\"",
            "mover_ch": "鍾國斌",
            "mover_en": "CHUNG Kwok-pan",
            "mover_type": "Member",
            "vote_separate_mechanism": "Yes",
            "gc_present_count": 34,
            "gc_vote_count": 33,
            "gc_yes_count": 8,
            "gc_no_count": 20,
            "gc_abstain_count": 5,
            "gc_result": "Negatived",
            "fc_present_count": 35,
            "fc_vote_count": 35,
            "fc_yes_count": 16,
            "fc_no_count": 8,
            "fc_abstain_count": 11,
            "fc_result": "Negatived",
            "overall_present_count": null,
            "overall_vote_count": null,
            "overall_yes_count": null,
            "overall_no_count": null,
            "overall_abstain_count": null,
            "overall_result": "Negatived",
            "name_ch": "石禮謙",
            "name_en": "Abraham SHEK",
            "constituency": "Functional",
            "vote": "Abstain",
            "display_order": 10
        },
        {
            "id": 48427,
            "start_date": "2012-11-07T00:00:00",
            "type": "Council Meeting",
            "term_no": 5,
            "vote_number": 11,
            "vote_date": "2012-11-07T00:00:00",
            "vote_time": "2012-11-07T23:58:46",
            "motion_ch": "田北俊議員對王國興議員的「完善房屋政策，解決市民住屋需要」議案作出的修正案",
            "motion_en": "AMENDMENT BY HON JAMES TIEN TO HON WONG KWOK-HING'S MOTION ON \"PERFECTING HOUSING POLICY AND RESOLVING PUBLIC HOUSING NEED\"",
            "mover_ch": "田北俊",
            "mover_en": "James TIEN",
            "mover_type": "Member",
            "vote_separate_mechanism": "Yes",
            "gc_present_count": 32,
            "gc_vote_count": 31,
            "gc_yes_count": 21,
            "gc_no_count": 4,
            "gc_abstain_count": 6,
            "gc_result": "Passed",
            "fc_present_count": 30,
            "fc_vote_count": 30,
            "fc_yes_count": 20,
            "fc_no_count": 2,
            "fc_abstain_count": 8,
            "fc_result": "Passed",
            "overall_present_count": null,
            "overall_vote_count": null,
            "overall_yes_count": null,
            "overall_no_count": null,
            "overall_abstain_count": null,
            "overall_result": "Passed",
            "name_ch": "石禮謙",
            "name_en": "Abraham SHEK",
            "constituency": "Functional",
            "vote": "Abstain",
            "display_order": 10
        },
        {
            "id": 48636,
            "start_date": "2012-11-14T00:00:00",
            "type": "Council Meeting",
            "term_no": 5,
            "vote_number": 2,
            "vote_date": "2012-11-14T00:00:00",
            "vote_time": "2012-11-14T23:14:44",
            "motion_ch": "馮檢基議員對陳婉嫻議員的「紓解貧窮」議案作出的修正案",
            "motion_en": "AMENDMENT BY HON FREDERICK FUNG TO HON CHAN YUEN-HAN'S MOTION ON \"ALLEVIATING POVERTY\"",
            "mover_ch": "馮檢基",
            "mover_en": "Frederick FUNG",
            "mover_type": "Member",
            "vote_separate_mechanism": "Yes",
            "gc_present_count": 34,
            "gc_vote_count": 33,
            "gc_yes_count": 29,
            "gc_no_count": 4,
            "gc_abstain_count": 0,
            "gc_result": "Passed",
            "fc_present_count": 33,
            "fc_vote_count": 33,
            "fc_yes_count": 17,
            "fc_no_count": 7,
            "fc_abstain_count": 9,
            "fc_result": "Passed",
            "overall_present_count": null,
            "overall_vote_count": null,
            "overall_yes_count": null,
            "overall_no_count": null,
            "overall_abstain_count": null,
            "overall_result": "Passed",
            "name_ch": "石禮謙",
            "name_en": "Abraham SHEK",
            "constituency": "Functional",
            "vote": "Abstain",
            "display_order": 10
        },
        {
            "id": 48846,
            "start_date": "2012-11-14T00:00:00",
            "type": "Council Meeting",
            "term_no": 5,
            "vote_number": 5,
            "vote_date": "2012-11-14T00:00:00",
            "vote_time": "2012-11-14T23:25:57",
            "motion_ch": "譚耀宗議員對陳婉嫻議員就「紓解貧窮」所提，經馮檢基議員修正的議案，作出的修正案",
            "motion_en": "AMENDMENT BY HON TAM YIU-CHUNG TO HON CHAN YUEN-HAN'S MOTION ON \"ALLEVIATING POVERTY\" AS AMENDED BY HON FREDERICK FUNG",
            "mover_ch": "譚耀宗",
            "mover_en": "TAM Yiu-chung",
            "mover_type": "Member",
            "vote_separate_mechanism": "Yes",
            "gc_present_count": 34,
            "gc_vote_count": 33,
            "gc_yes_count": 29,
            "gc_no_count": 3,
            "gc_abstain_count": 1,
            "gc_result": "Passed",
            "fc_present_count": 34,
            "fc_vote_count": 34,
            "fc_yes_count": 18,
            "fc_no_count": 5,
            "fc_abstain_count": 11,
            "fc_result": "Passed",
            "overall_present_count": null,
            "overall_vote_count": null,
            "overall_yes_count": null,
            "overall_no_count": null,
            "overall_abstain_count": null,
            "overall_result": "Passed",
            "name_ch": "石禮謙",
            "name_en": "Abraham SHEK",
            "constituency": "Functional",
            "vote": "Abstain",
            "display_order": 10
        },
        {
            "id": 51281,
            "start_date": "2012-12-05T00:00:00",
            "type": "Council Meeting",
            "term_no": 5,
            "vote_number": 10,
            "vote_date": "2012-12-06T00:00:00",
            "vote_time": "2012-12-06T13:48:36",
            "motion_ch": "單仲偕議員對張華峰議員就「支持證券業發展」所提，經王國興議員／湯家驊議員修正的議案，作出的修正案",
            "motion_en": "AMENDMENT BY HON SIN CHUNG-KAI TO HON CHRISTOPHER CHEUNG'S MOTION ON \"SUPPORTING THE DEVELOPMENT OF THE SECURITIES INDUSTRY\" AS AMENDED BY HON WONG KWOK-HING / HON RONNY TONG",
            "mover_ch": "單仲偕",
            "mover_en": "SIN Chung-kai",
            "mover_type": "Member",
            "vote_separate_mechanism": "Yes",
            "gc_present_count": 16,
            "gc_vote_count": 15,
            "gc_yes_count": 15,
            "gc_no_count": 0,
            "gc_abstain_count": 0,
            "gc_result": "Passed",
            "fc_present_count": 25,
            "fc_vote_count": 25,
            "fc_yes_count": 13,
            "fc_no_count": 6,
            "fc_abstain_count": 6,
            "fc_result": "Passed",
            "overall_present_count": null,
            "overall_vote_count": null,
            "overall_yes_count": null,
            "overall_no_count": null,
            "overall_abstain_count": null,
            "overall_result": "Passed",
            "name_ch": "石禮謙",
            "name_en": "Abraham SHEK",
            "constituency": "Functional",
            "vote": "Abstain",
            "display_order": 10
        },
        {
            "id": 53285,
            "start_date": "2013-01-23T00:00:00",
            "type": "Council Meeting",
            "term_no": 5,
            "vote_number": 3,
            "vote_date": "2013-01-23T00:00:00",
            "vote_time": "2013-01-23T19:43:54",
            "motion_ch": "梁繼昌議員對葛珮帆議員的「幫助中產」議案作出的修正案",
            "motion_en": "AMENDMENT BY HON KENNETH LEUNG TO DR HON ELIZABETH QUAT'S MOTION ON \"ASSISTING THE MIDDLE CLASS\"",
            "mover_ch": "梁繼昌",
            "mover_en": "Kenneth LEUNG",
            "mover_type": "Member",
            "vote_separate_mechanism": "Yes",
            "gc_present_count": 30,
            "gc_vote_count": 29,
            "gc_yes_count": 14,
            "gc_no_count": 0,
            "gc_abstain_count": 15,
            "gc_result": "Negatived",
            "fc_present_count": 28,
            "fc_vote_count": 28,
            "fc_yes_count": 15,
            "fc_no_count": 0,
            "fc_abstain_count": 13,
            "fc_result": "Passed",
            "overall_present_count": null,
            "overall_vote_count": null,
            "overall_yes_count": null,
            "overall_no_count": null,
            "overall_abstain_count": null,
            "overall_result": "Negatived",
            "name_ch": "石禮謙",
            "name_en": "Abraham SHEK",
            "constituency": "Functional",
            "vote": "Abstain",
            "display_order": 10
        },
        {
            "id": 53425,
            "start_date": "2013-01-23T00:00:00",
            "type": "Council Meeting",
            "term_no": 5,
            "vote_number": 5,
            "vote_date": "2013-01-23T00:00:00",
            "vote_time": "2013-01-23T19:48:15",
            "motion_ch": "單仲偕議員對葛珮帆議員的「幫助中產」議案作出的修正案",
            "motion_en": "AMENDMENT BY HON SIN CHUNG-KAI TO DR HON ELIZABETH QUAT'S MOTION ON \"ASSISTING THE MIDDLE CLASS\"",
            "mover_ch": "單仲偕",
            "mover_en": "SIN Chung-kai",
            "mover_type": "Member",
            "vote_separate_mechanism": "Yes",
            "gc_present_count": 30,
            "gc_vote_count": 29,
            "gc_yes_count": 26,
            "gc_no_count": 2,
            "gc_abstain_count": 1,
            "gc_result": "Passed",
            "fc_present_count": 27,
            "fc_vote_count": 27,
            "fc_yes_count": 16,
            "fc_no_count": 1,
            "fc_abstain_count": 10,
            "fc_result": "Passed",
            "overall_present_count": null,
            "overall_vote_count": null,
            "overall_yes_count": null,
            "overall_no_count": null,
            "overall_abstain_count": null,
            "overall_result": "Passed",
            "name_ch": "石禮謙",
            "name_en": "Abraham SHEK",
            "constituency": "Functional",
            "vote": "Abstain",
            "display_order": 10
        },
        {
            "id": 53495,
            "start_date": "2013-01-23T00:00:00",
            "type": "Council Meeting",
            "term_no": 5,
            "vote_number": 6,
            "vote_date": "2013-01-24T00:00:00",
            "vote_time": "2013-01-24T16:35:10",
            "motion_ch": "易志明議員對田北俊議員的「優化失業綜援」議案作出的修正案",
            "motion_en": "AMENDMENT BY HON FRANKIE YICK TO HON JAMES TIEN'S MOTION ON \"OPTIMIZING THE COMPREHENSIVE SOCIAL SECURITY ASSISTANCE FOR THE UNEMPLOYED\"",
            "mover_ch": "易志明",
            "mover_en": "Frankie YICK",
            "mover_type": "Member",
            "vote_separate_mechanism": "Yes",
            "gc_present_count": 27,
            "gc_vote_count": 26,
            "gc_yes_count": 2,
            "gc_no_count": 18,
            "gc_abstain_count": 6,
            "gc_result": "Negatived",
            "fc_present_count": 26,
            "fc_vote_count": 26,
            "fc_yes_count": 3,
            "fc_no_count": 9,
            "fc_abstain_count": 14,
            "fc_result": "Negatived",
            "overall_present_count": null,
            "overall_vote_count": null,
            "overall_yes_count": null,
            "overall_no_count": null,
            "overall_abstain_count": null,
            "overall_result": "Negatived",
            "name_ch": "石禮謙",
            "name_en": "Abraham SHEK",
            "constituency": "Functional",
            "vote": "Abstain",
            "display_order": 10
        },
        {
            "id": 53565,
            "start_date": "2013-01-23T00:00:00",
            "type": "Council Meeting",
            "term_no": 5,
            "vote_number": 7,
            "vote_date": "2013-01-24T00:00:00",
            "vote_time": "2013-01-24T16:38:12",
            "motion_ch": "張超雄議員對田北俊議員的「優化失業綜援」議案作出的修正案",
            "motion_en": "AMENDMENT BY DR HON FERNANDO CHEUNG TO HON JAMES TIEN'S MOTION ON \"OPTIMIZING THE COMPREHENSIVE SOCIAL SECURITY ASSISTANCE FOR THE UNEMPLOYED\"",
            "mover_ch": "張超雄",
            "mover_en": "Dr Fernando CHEUNG",
            "mover_type": "Member",
            "vote_separate_mechanism": "Yes",
            "gc_present_count": 27,
            "gc_vote_count": 26,
            "gc_yes_count": 25,
            "gc_no_count": 0,
            "gc_abstain_count": 1,
            "gc_result": "Passed",
            "fc_present_count": 26,
            "fc_vote_count": 26,
            "fc_yes_count": 19,
            "fc_no_count": 0,
            "fc_abstain_count": 7,
            "fc_result": "Passed",
            "overall_present_count": null,
            "overall_vote_count": null,
            "overall_yes_count": null,
            "overall_no_count": null,
            "overall_abstain_count": null,
            "overall_result": "Passed",
            "name_ch": "石禮謙",
            "name_en": "Abraham SHEK",
            "constituency": "Functional",
            "vote": "Abstain",
            "display_order": 10
        },
        {
            "id": 54475,
            "start_date": "2013-02-06T00:00:00",
            "type": "Council Meeting",
            "term_no": 5,
            "vote_number": 4,
            "vote_date": "2013-02-07T00:00:00",
            "vote_time": "2013-02-07T00:33:25",
            "motion_ch": "王國興議員對方剛議員的「增加零售業經營面積」議案作出的修正案",
            "motion_en": "AMENDMENT BY HON WONG KWOK-HING TO HON VINCENT FANG'S MOTION ON \"INCREASING THE BUSINESS FLOOR AREAS OF THE RETAIL INDUSTRY\"",
            "mover_ch": "王國興",
            "mover_en": "WONG Kwok-hing",
            "mover_type": "Member",
            "vote_separate_mechanism": "Yes",
            "gc_present_count": 24,
            "gc_vote_count": 23,
            "gc_yes_count": 19,
            "gc_no_count": 4,
            "gc_abstain_count": 0,
            "gc_result": "Passed",
            "fc_present_count": 25,
            "fc_vote_count": 25,
            "fc_yes_count": 17,
            "fc_no_count": 1,
            "fc_abstain_count": 7,
            "fc_result": "Passed",
            "overall_present_count": null,
            "overall_vote_count": null,
            "overall_yes_count": null,
            "overall_no_count": null,
            "overall_abstain_count": null,
            "overall_result": "Passed",
            "name_ch": "石禮謙",
            "name_en": "Abraham SHEK",
            "constituency": "Functional",
            "vote": "Abstain",
            "display_order": 10
        },
        {
            "id": 55175,
            "start_date": "2013-02-20T00:00:00",
            "type": "Council Meeting",
            "term_no": 5,
            "vote_number": 8,
            "vote_date": "2013-02-21T00:00:00",
            "vote_time": "2013-02-21T15:40:44",
            "motion_ch": "李卓人議員對潘兆平議員的「保障職業安全」議案作出的修正案",
            "motion_en": "AMENDMENT BY HON LEE CHEUK-YAN TO HON POON SIU-PING'S MOTION ON \"ENSURING OCCUPATIONAL SAFETY\"",
            "mover_ch": "李卓人",
            "mover_en": "LEE Cheuk-yan",
            "mover_type": "Member",
            "vote_separate_mechanism": "Yes",
            "gc_present_count": 24,
            "gc_vote_count": 23,
            "gc_yes_count": 22,
            "gc_no_count": 1,
            "gc_abstain_count": 0,
            "gc_result": "Passed",
            "fc_present_count": 23,
            "fc_vote_count": 23,
            "fc_yes_count": 10,
            "fc_no_count": 3,
            "fc_abstain_count": 10,
            "fc_result": "Negatived",
            "overall_present_count": null,
            "overall_vote_count": null,
            "overall_yes_count": null,
            "overall_no_count": null,
            "overall_abstain_count": null,
            "overall_result": "Negatived",
            "name_ch": "石禮謙",
            "name_en": "Abraham SHEK",
            "constituency": "Functional",
            "vote": "Abstain",
            "display_order": 10
        },
        {
            "id": 55245,
            "start_date": "2013-02-20T00:00:00",
            "type": "Council Meeting",
            "term_no": 5,
            "vote_number": 9,
            "vote_date": "2013-02-21T00:00:00",
            "vote_time": "2013-02-21T15:47:15",
            "motion_ch": "縮短點名表決響鐘時間的議案",
            "motion_en": "MOTION TO SHORTEN DURATION OF DIVISION BELL",
            "mover_ch": "梁君彥",
            "mover_en": "Andrew LEUNG",
            "mover_type": "Member",
            "vote_separate_mechanism": "Yes",
            "gc_present_count": 24,
            "gc_vote_count": 23,
            "gc_yes_count": 23,
            "gc_no_count": 0,
            "gc_abstain_count": 0,
            "gc_result": "Passed",
            "fc_present_count": 22,
            "fc_vote_count": 22,
            "fc_yes_count": 21,
            "fc_no_count": 0,
            "fc_abstain_count": 1,
            "fc_result": "Passed",
            "overall_present_count": null,
            "overall_vote_count": null,
            "overall_yes_count": null,
            "overall_no_count": null,
            "overall_abstain_count": null,
            "overall_result": "Passed",
            "name_ch": "石禮謙",
            "name_en": "Abraham SHEK",
            "constituency": "Functional",
            "vote": "Abstain",
            "display_order": 10
        },
        {
            "id": 55595,
            "start_date": "2013-03-20T00:00:00",
            "type": "Council Meeting",
            "term_no": 5,
            "vote_number": 3,
            "vote_date": "2013-03-20T00:00:00",
            "vote_time": "2013-03-20T20:09:10",
            "motion_ch": "葉建源議員對廖長江議員就「推動香港經濟轉型」所提，經梁繼昌議員／張華峰議員／鄧家彪議員／單仲偕議員修正的議案，作出的修正案",
            "motion_en": "AMENDMENT BY HON IP KIN-YUEN TO HON MARTIN LIAO'S MOTION ON \"PROMOTING HONG KONG'S ECONOMIC RESTRUCTURING\" AS AMENDED BY HON KENNETH LEUNG / HON CHRISTOPHER CHEUNG / HON TANG KA-PIU / HON SIN CHUNG-KAI",
            "mover_ch": "葉建源",
            "mover_en": "IP Kin-yuen",
            "mover_type": "Member",
            "vote_separate_mechanism": "Yes",
            "gc_present_count": 30,
            "gc_vote_count": 29,
            "gc_yes_count": 20,
            "gc_no_count": 0,
            "gc_abstain_count": 9,
            "gc_result": "Passed",
            "fc_present_count": 30,
            "fc_vote_count": 30,
            "fc_yes_count": 17,
            "fc_no_count": 1,
            "fc_abstain_count": 12,
            "fc_result": "Passed",
            "overall_present_count": null,
            "overall_vote_count": null,
            "overall_yes_count": null,
            "overall_no_count": null,
            "overall_abstain_count": null,
            "overall_result": "Passed",
            "name_ch": "石禮謙",
            "name_en": "Abraham SHEK",
            "constituency": "Functional",
            "vote": "Abstain",
            "display_order": 10
        },
        {
            "id": 55665,
            "start_date": "2013-03-20T00:00:00",
            "type": "Council Meeting",
            "term_no": 5,
            "vote_number": 4,
            "vote_date": "2013-03-20T00:00:00",
            "vote_time": "2013-03-20T23:39:31",
            "motion_ch": "梁家傑議員對黃國健議員就「落實啟德規劃，配合九龍東發展」所提，經馮檢基議員／陳鑑林議員／易志明議員／胡志偉議員修正的議案，作出的修正案",
            "motion_en": "AMENDMENT BY HON ALAN LEONG TO HON WONG KWOK-KIN'S MOTION ON \"IMPLEMENTING THE KAI TAK PLANNING TO DOVETAIL WITH KOWLOON EAST DEVELOPMENT\" AS AMENDED BY HON FREDERICK FUNG / HON CHAN KAM-LAM / HON FRANKIE YICK / HON WU CHI-WAI",
            "mover_ch": "梁家傑",
            "mover_en": "Alan LEONG",
            "mover_type": "Member",
            "vote_separate_mechanism": "Yes",
            "gc_present_count": 22,
            "gc_vote_count": 21,
            "gc_yes_count": 11,
            "gc_no_count": 2,
            "gc_abstain_count": 8,
            "gc_result": "Negatived",
            "fc_present_count": 20,
            "fc_vote_count": 20,
            "fc_yes_count": 11,
            "fc_no_count": 0,
            "fc_abstain_count": 9,
            "fc_result": "Passed",
            "overall_present_count": null,
            "overall_vote_count": null,
            "overall_yes_count": null,
            "overall_no_count": null,
            "overall_abstain_count": null,
            "overall_result": "Negatived",
            "name_ch": "石禮謙",
            "name_en": "Abraham SHEK",
            "constituency": "Functional",
            "vote": "Abstain",
            "display_order": 10
        },
        {
            "id": 104805,
            "start_date": "2013-05-29T00:00:00",
            "type": "Council Meeting",
            "term_no": 5,
            "vote_number": 1,
            "vote_date": "2013-05-29T00:00:00",
            "vote_time": "2013-05-29T17:25:11",
            "motion_ch": "「六四事件」議案",
            "motion_en": "MOTION ON \"THE 4 JUNE INCIDENT\"",
            "mover_ch": "何俊仁",
            "mover_en": "Albert HO",
            "mover_type": "Member",
            "vote_separate_mechanism": "Yes",
            "gc_present_count": 29,
            "gc_vote_count": 28,
            "gc_yes_count": 17,
            "gc_no_count": 6,
            "gc_abstain_count": 5,
            "gc_result": "Passed",
            "fc_present_count": 27,
            "fc_vote_count": 27,
            "fc_yes_count": 8,
            "fc_no_count": 6,
            "fc_abstain_count": 13,
            "fc_result": "Negatived",
            "overall_present_count": null,
            "overall_vote_count": null,
            "overall_yes_count": null,
            "overall_no_count": null,
            "overall_abstain_count": null,
            "overall_result": "Negatived",
            "name_ch": "石禮謙",
            "name_en": "Abraham SHEK",
            "constituency": "Functional",
            "vote": "Abstain",
            "display_order": 10
        },
        {
            "id": 105715,
            "start_date": "2013-06-05T00:00:00",
            "type": "Council Meeting",
            "term_no": 5,
            "vote_number": 6,
            "vote_date": "2013-06-05T00:00:00",
            "vote_time": "2013-06-05T18:19:49",
            "motion_ch": "李慧琼議員動議，經王國興議員／張國柱議員／毛孟靜議員修正的「積極推動家庭友善政策」議案",
            "motion_en": "MOTION MOVED BY HON STARRY LEE ON \"ACTIVELY PROMOTING FAMILY-FRIENDLY POLICIES\" AS AMENDED BY HON WONG KWOK-HING / HON CHEUNG KWOK-CHE / HON CLAUDIA MO",
            "mover_ch": "李慧琼",
            "mover_en": "Starry LEE",
            "mover_type": "Member",
            "vote_separate_mechanism": "Yes",
            "gc_present_count": 28,
            "gc_vote_count": 27,
            "gc_yes_count": 26,
            "gc_no_count": 1,
            "gc_abstain_count": 0,
            "gc_result": "Passed",
            "fc_present_count": 33,
            "fc_vote_count": 33,
            "fc_yes_count": 23,
            "fc_no_count": 3,
            "fc_abstain_count": 7,
            "fc_result": "Passed",
            "overall_present_count": null,
            "overall_vote_count": null,
            "overall_yes_count": null,
            "overall_no_count": null,
            "overall_abstain_count": null,
            "overall_result": "Passed",
            "name_ch": "石禮謙",
            "name_en": "Abraham SHEK",
            "constituency": "Functional",
            "vote": "Abstain",
            "display_order": 10
        },
        {
            "id": 107815,
            "start_date": "2013-07-03T00:00:00",
            "type": "Council Meeting",
            "term_no": 5,
            "vote_number": 3,
            "vote_date": "2013-07-03T00:00:00",
            "vote_time": "2013-07-03T19:31:45",
            "motion_ch": "「正視七一遊行市民的訴求」議案",
            "motion_en": "MOTION ON \"FACING UP TO THE ASPIRATIONS OF THE PEOPLE PARTICIPATING IN THE MARCH ON 1 JULY\"",
            "mover_ch": "單仲偕",
            "mover_en": "SIN Chung-kai",
            "mover_type": "Member",
            "vote_separate_mechanism": "Yes",
            "gc_present_count": 31,
            "gc_vote_count": 30,
            "gc_yes_count": 18,
            "gc_no_count": 0,
            "gc_abstain_count": 12,
            "gc_result": "Passed",
            "fc_present_count": 32,
            "fc_vote_count": 32,
            "fc_yes_count": 14,
            "fc_no_count": 1,
            "fc_abstain_count": 17,
            "fc_result": "Negatived",
            "overall_present_count": null,
            "overall_vote_count": null,
            "overall_yes_count": null,
            "overall_no_count": null,
            "overall_abstain_count": null,
            "overall_result": "Negatived",
            "name_ch": "石禮謙",
            "name_en": "Abraham SHEK",
            "constituency": "Functional",
            "vote": "Abstain",
            "display_order": 10
        },
        {
            "id": 108095,
            "start_date": "2013-07-03T00:00:00",
            "type": "Council Meeting",
            "term_no": 5,
            "vote_number": 7,
            "vote_date": "2013-07-03T00:00:00",
            "vote_time": "2013-07-03T23:49:04",
            "motion_ch": "葉建源議員對葉國謙議員就「制訂人口政策」所提，經陳家洛議員修正的議案，作出的修正案",
            "motion_en": "AMENDMENT BY HON IP KIN-YUEN TO HON IP KWOK-HIM'S MOTION ON \"FORMULATING A POPULATION POLICY\" AS AMENDED BY DR HON KENNETH CHAN",
            "mover_ch": "葉建源",
            "mover_en": "IP Kin-yuen",
            "mover_type": "Member",
            "vote_separate_mechanism": "Yes",
            "gc_present_count": 29,
            "gc_vote_count": 28,
            "gc_yes_count": 19,
            "gc_no_count": 0,
            "gc_abstain_count": 9,
            "gc_result": "Passed",
            "fc_present_count": 31,
            "fc_vote_count": 31,
            "fc_yes_count": 20,
            "fc_no_count": 1,
            "fc_abstain_count": 10,
            "fc_result": "Passed",
            "overall_present_count": null,
            "overall_vote_count": null,
            "overall_yes_count": null,
            "overall_no_count": null,
            "overall_abstain_count": null,
            "overall_result": "Passed",
            "name_ch": "石禮謙",
            "name_en": "Abraham SHEK",
            "constituency": "Functional",
            "vote": "Abstain",
            "display_order": 10
        },
        {
            "id": 108305,
            "start_date": "2013-07-03T00:00:00",
            "type": "Council Meeting",
            "term_no": 5,
            "vote_number": 10,
            "vote_date": "2013-07-03T00:00:00",
            "vote_time": "2013-07-03T23:56:15",
            "motion_ch": "梁繼昌議員對葉國謙議員就「制訂人口政策」所提，經陳家洛議員／葉建源議員修正的議案，作出的修正案",
            "motion_en": "AMENDMENT BY HON KENNETH LEUNG TO HON IP KWOK-HIM'S MOTION ON \"FORMULATING A POPULATION POLICY\" AS AMENDED BY DR HON KENNETH CHAN / HON IP KIN-YUEN",
            "mover_ch": "梁繼昌",
            "mover_en": "Kenneth LEUNG",
            "mover_type": "Member",
            "vote_separate_mechanism": "Yes",
            "gc_present_count": 30,
            "gc_vote_count": 29,
            "gc_yes_count": 20,
            "gc_no_count": 0,
            "gc_abstain_count": 9,
            "gc_result": "Passed",
            "fc_present_count": 31,
            "fc_vote_count": 31,
            "fc_yes_count": 19,
            "fc_no_count": 0,
            "fc_abstain_count": 12,
            "fc_result": "Passed",
            "overall_present_count": null,
            "overall_vote_count": null,
            "overall_yes_count": null,
            "overall_no_count": null,
            "overall_abstain_count": null,
            "overall_result": "Passed",
            "name_ch": "石禮謙",
            "name_en": "Abraham SHEK",
            "constituency": "Functional",
            "vote": "Abstain",
            "display_order": 10
        },
        {
            "id": 108375,
            "start_date": "2013-07-03T00:00:00",
            "type": "Council Meeting",
            "term_no": 5,
            "vote_number": 11,
            "vote_date": "2013-07-04T00:00:00",
            "vote_time": "2013-07-04T00:00:26",
            "motion_ch": "葉國謙議員動議，經陳家洛議員／葉建源議員／梁繼昌議員修正的「制訂人口政策」議案",
            "motion_en": "MOTION MOVED BY HON IP KWOK-HIM ON \"FORMULATING A POPULATION POLICY\" AS AMENDED BY DR HON KENNETH CHAN / HON IP KIN-YUEN / HON KENNETH LEUNG",
            "mover_ch": "葉國謙",
            "mover_en": "IP Kwok-him",
            "mover_type": "Member",
            "vote_separate_mechanism": "Yes",
            "gc_present_count": 28,
            "gc_vote_count": 27,
            "gc_yes_count": 14,
            "gc_no_count": 1,
            "gc_abstain_count": 12,
            "gc_result": "Negatived",
            "fc_present_count": 31,
            "fc_vote_count": 31,
            "fc_yes_count": 18,
            "fc_no_count": 0,
            "fc_abstain_count": 13,
            "fc_result": "Passed",
            "overall_present_count": null,
            "overall_vote_count": null,
            "overall_yes_count": null,
            "overall_no_count": null,
            "overall_abstain_count": null,
            "overall_result": "Negatived",
            "name_ch": "石禮謙",
            "name_en": "Abraham SHEK",
            "constituency": "Functional",
            "vote": "Abstain",
            "display_order": 10
        },
        {
            "id": 109635,
            "start_date": "2013-10-09T00:00:00",
            "type": "Council Meeting",
            "term_no": 5,
            "vote_number": 2,
            "vote_date": "2013-10-10T00:00:00",
            "vote_time": "2013-10-10T18:47:13",
            "motion_ch": "莫乃光議員對盧偉國議員的「制訂長遠基建規劃，推動可持續發展」議案作出的修正案",
            "motion_en": "AMENDMENT BY HON CHARLES PETER MOK TO IR DR HON LO WAI-KWOK'S MOTION ON \"FORMULATING LONG-TERM INFRASTRUCTURE PLANNING TO PROMOTE SUSTAINABLE DEVELOPMENT\"",
            "mover_ch": "莫乃光",
            "mover_en": "Charles Peter MOK",
            "mover_type": "Member",
            "vote_separate_mechanism": "Yes",
            "gc_present_count": 27,
            "gc_vote_count": 26,
            "gc_yes_count": 14,
            "gc_no_count": 0,
            "gc_abstain_count": 12,
            "gc_result": "Passed",
            "fc_present_count": 32,
            "fc_vote_count": 32,
            "fc_yes_count": 14,
            "fc_no_count": 0,
            "fc_abstain_count": 18,
            "fc_result": "Negatived",
            "overall_present_count": null,
            "overall_vote_count": null,
            "overall_yes_count": null,
            "overall_no_count": null,
            "overall_abstain_count": null,
            "overall_result": "Negatived",
            "name_ch": "石禮謙",
            "name_en": "Abraham SHEK",
            "constituency": "Functional",
            "vote": "Abstain",
            "display_order": 10
        },
        {
            "id": 110195,
            "start_date": "2013-10-16T00:00:00",
            "type": "Council Meeting",
            "term_no": 5,
            "vote_number": 4,
            "vote_date": "2013-10-16T00:00:00",
            "vote_time": "2013-10-16T22:21:48",
            "motion_ch": "湯家驊議員對梁繼昌議員就「善用公共財政，加強香港經濟創意動力」所提，經葛珮帆議員／梁君彥議員修正的議案，作出的修正案",
            "motion_en": "AMENDMENT BY HON RONNY TONG TO HON KENNETH LEUNG'S MOTION ON \"OPTIMIZING PUBLIC FINANCES AND ENHANCING THE IMPETUS FOR INNOVATION IN HONG KONG'S ECONOMY\" AS AMENDED BY DR HON ELIZABETH QUAT / HON ANDREW LEUNG",
            "mover_ch": "湯家驊",
            "mover_en": "Ronny TONG",
            "mover_type": "Member",
            "vote_separate_mechanism": "Yes",
            "gc_present_count": 29,
            "gc_vote_count": 28,
            "gc_yes_count": 23,
            "gc_no_count": 0,
            "gc_abstain_count": 5,
            "gc_result": "Passed",
            "fc_present_count": 26,
            "fc_vote_count": 26,
            "fc_yes_count": 18,
            "fc_no_count": 0,
            "fc_abstain_count": 8,
            "fc_result": "Passed",
            "overall_present_count": null,
            "overall_vote_count": null,
            "overall_yes_count": null,
            "overall_no_count": null,
            "overall_abstain_count": null,
            "overall_result": "Passed",
            "name_ch": "石禮謙",
            "name_en": "Abraham SHEK",
            "constituency": "Functional",
            "vote": "Abstain",
            "display_order": 10
        },
        {
            "id": 110265,
            "start_date": "2013-10-16T00:00:00",
            "type": "Council Meeting",
            "term_no": 5,
            "vote_number": 5,
            "vote_date": "2013-10-16T00:00:00",
            "vote_time": "2013-10-16T22:24:14",
            "motion_ch": "何秀蘭議員對梁繼昌議員就「善用公共財政，加強香港經濟創意動力」所提，經葛珮帆議員／梁君彥議員／湯家驊議員修正的議案，作出的修正案",
            "motion_en": "AMENDMENT BY HON CYD HO TO HON KENNETH LEUNG'S MOTION ON \"OPTIMIZING PUBLIC FINANCES AND ENHANCING THE IMPETUS FOR INNOVATION IN HONG KONG'S ECONOMY\" AS AMENDED BY DR HON ELIZABETH QUAT / HON ANDREW LEUNG / HON RONNY TONG",
            "mover_ch": "何秀蘭",
            "mover_en": "Cyd HO",
            "mover_type": "Member",
            "vote_separate_mechanism": "Yes",
            "gc_present_count": 29,
            "gc_vote_count": 28,
            "gc_yes_count": 13,
            "gc_no_count": 1,
            "gc_abstain_count": 14,
            "gc_result": "Negatived",
            "fc_present_count": 26,
            "fc_vote_count": 26,
            "fc_yes_count": 6,
            "fc_no_count": 1,
            "fc_abstain_count": 19,
            "fc_result": "Negatived",
            "overall_present_count": null,
            "overall_vote_count": null,
            "overall_yes_count": null,
            "overall_no_count": null,
            "overall_abstain_count": null,
            "overall_result": "Negatived",
            "name_ch": "石禮謙",
            "name_en": "Abraham SHEK",
            "constituency": "Functional",
            "vote": "Abstain",
            "display_order": 10
        },
        {
            "id": 110335,
            "start_date": "2013-10-16T00:00:00",
            "type": "Council Meeting",
            "term_no": 5,
            "vote_number": 6,
            "vote_date": "2013-10-16T00:00:00",
            "vote_time": "2013-10-16T22:26:39",
            "motion_ch": "莫乃光議員對梁繼昌議員就「善用公共財政，加強香港經濟創意動力」所提，經葛珮帆議員／梁君彥議員／湯家驊議員修正的議案，作出的修正案",
            "motion_en": "AMENDMENT BY HON CHARLES PETER MOK TO HON KENNETH LEUNG'S MOTION ON \"OPTIMIZING PUBLIC FINANCES AND ENHANCING THE IMPETUS FOR INNOVATION IN HONG KONG'S ECONOMY\" AS AMENDED BY DR HON ELIZABETH QUAT / HON ANDREW LEUNG / HON RONNY TONG",
            "mover_ch": "莫乃光",
            "mover_en": "Charles Peter MOK",
            "mover_type": "Member",
            "vote_separate_mechanism": "Yes",
            "gc_present_count": 29,
            "gc_vote_count": 28,
            "gc_yes_count": 22,
            "gc_no_count": 0,
            "gc_abstain_count": 6,
            "gc_result": "Passed",
            "fc_present_count": 26,
            "fc_vote_count": 26,
            "fc_yes_count": 14,
            "fc_no_count": 1,
            "fc_abstain_count": 11,
            "fc_result": "Passed",
            "overall_present_count": null,
            "overall_vote_count": null,
            "overall_yes_count": null,
            "overall_no_count": null,
            "overall_abstain_count": null,
            "overall_result": "Passed",
            "name_ch": "石禮謙",
            "name_en": "Abraham SHEK",
            "constituency": "Functional",
            "vote": "Abstain",
            "display_order": 10
        },
        {
            "id": 111035,
            "start_date": "2013-10-30T00:00:00",
            "type": "Council Meeting",
            "term_no": 5,
            "vote_number": 2,
            "vote_date": "2013-10-30T00:00:00",
            "vote_time": "2013-10-30T18:11:55",
            "motion_ch": "黃碧雲議員對陳志全議員的「跨性別婚姻」議案作出的修正案",
            "motion_en": "AMENDMENT BY DR HON HELENA WONG TO HON CHAN CHI-CHUEN'S MOTION ON \"TRANSGENDER MARRIAGE\"",
            "mover_ch": "黃碧雲",
            "mover_en": "Dr Helena WONG",
            "mover_type": "Member",
            "vote_separate_mechanism": "Yes",
            "gc_present_count": 29,
            "gc_vote_count": 28,
            "gc_yes_count": 7,
            "gc_no_count": 11,
            "gc_abstain_count": 10,
            "gc_result": "Negatived",
            "fc_present_count": 30,
            "fc_vote_count": 30,
            "fc_yes_count": 8,
            "fc_no_count": 5,
            "fc_abstain_count": 17,
            "fc_result": "Negatived",
            "overall_present_count": null,
            "overall_vote_count": null,
            "overall_yes_count": null,
            "overall_no_count": null,
            "overall_abstain_count": null,
            "overall_result": "Negatived",
            "name_ch": "石禮謙",
            "name_en": "Abraham SHEK",
            "constituency": "Functional",
            "vote": "Abstain",
            "display_order": 10
        },
        {
            "id": 111315,
            "start_date": "2013-10-30T00:00:00",
            "type": "Council Meeting",
            "term_no": 5,
            "vote_number": 6,
            "vote_date": "2013-10-30T00:00:00",
            "vote_time": "2013-10-30T23:21:30",
            "motion_ch": "梁繼昌議員對范國威議員的「制訂政策時需以'港人優先'為依歸」議案作出的修正案",
            "motion_en": "AMENDMENT BY HON KENNETH LEUNG TO HON GARY FAN'S MOTION ON \"ADHERING TO THE NEED TO 'PUT HONG KONG PEOPLE FIRST' IN FORMULATING POLICIES\"",
            "mover_ch": "梁繼昌",
            "mover_en": "Kenneth LEUNG",
            "mover_type": "Member",
            "vote_separate_mechanism": "Yes",
            "gc_present_count": 29,
            "gc_vote_count": 28,
            "gc_yes_count": 17,
            "gc_no_count": 2,
            "gc_abstain_count": 9,
            "gc_result": "Passed",
            "fc_present_count": 24,
            "fc_vote_count": 24,
            "fc_yes_count": 13,
            "fc_no_count": 2,
            "fc_abstain_count": 9,
            "fc_result": "Passed",
            "overall_present_count": null,
            "overall_vote_count": null,
            "overall_yes_count": null,
            "overall_no_count": null,
            "overall_abstain_count": null,
            "overall_result": "Passed",
            "name_ch": "石禮謙",
            "name_en": "Abraham SHEK",
            "constituency": "Functional",
            "vote": "Abstain",
            "display_order": 10
        },
        {
            "id": 111385,
            "start_date": "2013-10-30T00:00:00",
            "type": "Council Meeting",
            "term_no": 5,
            "vote_number": 7,
            "vote_date": "2013-10-30T00:00:00",
            "vote_time": "2013-10-30T23:24:48",
            "motion_ch": "何俊仁議員對范國威議員就「制訂政策時需以'港人優先'為依歸」所提，經梁繼昌議員修正的議案，作出的修正案",
            "motion_en": "AMENDMENT BY HON ALBERT HO TO HON GARY FAN'S MOTION ON \"ADHERING TO THE NEED TO 'PUT HONG KONG PEOPLE FIRST' IN FORMULATING POLICIES\" AS AMENDED BY HON KENNETH LEUNG",
            "mover_ch": "何俊仁",
            "mover_en": "Albert HO",
            "mover_type": "Member",
            "vote_separate_mechanism": "Yes",
            "gc_present_count": 29,
            "gc_vote_count": 28,
            "gc_yes_count": 13,
            "gc_no_count": 1,
            "gc_abstain_count": 14,
            "gc_result": "Negatived",
            "fc_present_count": 24,
            "fc_vote_count": 24,
            "fc_yes_count": 12,
            "fc_no_count": 1,
            "fc_abstain_count": 11,
            "fc_result": "Negatived",
            "overall_present_count": null,
            "overall_vote_count": null,
            "overall_yes_count": null,
            "overall_no_count": null,
            "overall_abstain_count": null,
            "overall_result": "Negatived",
            "name_ch": "石禮謙",
            "name_en": "Abraham SHEK",
            "constituency": "Functional",
            "vote": "Abstain",
            "display_order": 10
        },
        {
            "id": 111595,
            "start_date": "2013-10-30T00:00:00",
            "type": "Council Meeting",
            "term_no": 5,
            "vote_number": 10,
            "vote_date": "2013-10-30T00:00:00",
            "vote_time": "2013-10-30T23:32:03",
            "motion_ch": "張超雄議員對范國威議員就「制訂政策時需以'港人優先'為依歸」所提，經梁繼昌議員修正的議案，作出的修正案",
            "motion_en": "AMENDMENT BY DR HON FERNANDO CHEUNG TO HON GARY FAN'S MOTION ON \"ADHERING TO THE NEED TO 'PUT HONG KONG PEOPLE FIRST' IN FORMULATING POLICIES\" AS AMENDED BY HON KENNETH LEUNG",
            "mover_ch": "張超雄",
            "mover_en": "Dr Fernando CHEUNG",
            "mover_type": "Member",
            "vote_separate_mechanism": "Yes",
            "gc_present_count": 29,
            "gc_vote_count": 28,
            "gc_yes_count": 15,
            "gc_no_count": 2,
            "gc_abstain_count": 11,
            "gc_result": "Passed",
            "fc_present_count": 24,
            "fc_vote_count": 24,
            "fc_yes_count": 10,
            "fc_no_count": 4,
            "fc_abstain_count": 10,
            "fc_result": "Negatived",
            "overall_present_count": null,
            "overall_vote_count": null,
            "overall_yes_count": null,
            "overall_no_count": null,
            "overall_abstain_count": null,
            "overall_result": "Negatived",
            "name_ch": "石禮謙",
            "name_en": "Abraham SHEK",
            "constituency": "Functional",
            "vote": "Abstain",
            "display_order": 10
        },
        {
            "id": 112085,
            "start_date": "2013-11-06T00:00:00",
            "type": "Council Meeting",
            "term_no": 5,
            "vote_number": 6,
            "vote_date": "2013-11-07T00:00:00",
            "vote_time": "2013-11-07T23:07:27",
            "motion_ch": "葉劉淑儀議員對陳偉業議員就「經濟制裁菲律賓，還港人尊嚴」所提，經麥美娟議員／單仲偕議員修正的議案，作出的修正案",
            "motion_en": "AMENDMENT BY HON MRS REGINA IP TO HON ALBERT CHAN'S MOTION ON \"IMPOSING ECONOMIC SANCTIONS ON THE PHILIPPINES AND RESTORING HONG KONG PEOPLE'S DIGNITY\" AS AMENDED BY HON ALICE MAK / HON SIN CHUNG-KAI",
            "mover_ch": "葉劉淑儀",
            "mover_en": "Mrs Regina IP",
            "mover_type": "Member",
            "vote_separate_mechanism": "Yes",
            "gc_present_count": 28,
            "gc_vote_count": 27,
            "gc_yes_count": 21,
            "gc_no_count": 2,
            "gc_abstain_count": 4,
            "gc_result": "Passed",
            "fc_present_count": 24,
            "fc_vote_count": 24,
            "fc_yes_count": 20,
            "fc_no_count": 1,
            "fc_abstain_count": 3,
            "fc_result": "Passed",
            "overall_present_count": null,
            "overall_vote_count": null,
            "overall_yes_count": null,
            "overall_no_count": null,
            "overall_abstain_count": null,
            "overall_result": "Passed",
            "name_ch": "石禮謙",
            "name_en": "Abraham SHEK",
            "constituency": "Functional",
            "vote": "Abstain",
            "display_order": 10
        },
        {
            "id": 115865,
            "start_date": "2014-01-22T00:00:00",
            "type": "Council Meeting",
            "term_no": 5,
            "vote_number": 5,
            "vote_date": "2014-01-23T00:00:00",
            "vote_time": "2014-01-23T00:20:23",
            "motion_ch": "涂謹申議員對梁家傑議員的「捍衞編輯採訪獨立自主」議案作出的修正案",
            "motion_en": "AMENDMENT BY HON JAMES TO TO HON ALAN LEONG'S MOTION ON \"SAFEGUARDING EDITORIAL INDEPENDENCE AND AUTONOMY\"",
            "mover_ch": "涂謹申",
            "mover_en": "James TO",
            "mover_type": "Member",
            "vote_separate_mechanism": "Yes",
            "gc_present_count": 31,
            "gc_vote_count": 30,
            "gc_yes_count": 20,
            "gc_no_count": 8,
            "gc_abstain_count": 2,
            "gc_result": "Passed",
            "fc_present_count": 27,
            "fc_vote_count": 27,
            "fc_yes_count": 9,
            "fc_no_count": 8,
            "fc_abstain_count": 10,
            "fc_result": "Negatived",
            "overall_present_count": null,
            "overall_vote_count": null,
            "overall_yes_count": null,
            "overall_no_count": null,
            "overall_abstain_count": null,
            "overall_result": "Negatived",
            "name_ch": "石禮謙",
            "name_en": "Abraham SHEK",
            "constituency": "Functional",
            "vote": "Abstain",
            "display_order": 10
        },
        {
            "id": 115935,
            "start_date": "2014-01-22T00:00:00",
            "type": "Council Meeting",
            "term_no": 5,
            "vote_number": 6,
            "vote_date": "2014-01-23T00:00:00",
            "vote_time": "2014-01-23T00:22:23",
            "motion_ch": "何秀蘭議員對梁家傑議員的「捍衞編輯採訪獨立自主」議案作出的修正案",
            "motion_en": "AMENDMENT BY HON CYD HO TO HON ALAN LEONG'S MOTION ON \"SAFEGUARDING EDITORIAL INDEPENDENCE AND AUTONOMY\"",
            "mover_ch": "何秀蘭",
            "mover_en": "Cyd HO",
            "mover_type": "Member",
            "vote_separate_mechanism": "Yes",
            "gc_present_count": 31,
            "gc_vote_count": 30,
            "gc_yes_count": 17,
            "gc_no_count": 12,
            "gc_abstain_count": 1,
            "gc_result": "Passed",
            "fc_present_count": 27,
            "fc_vote_count": 27,
            "fc_yes_count": 8,
            "fc_no_count": 13,
            "fc_abstain_count": 6,
            "fc_result": "Negatived",
            "overall_present_count": null,
            "overall_vote_count": null,
            "overall_yes_count": null,
            "overall_no_count": null,
            "overall_abstain_count": null,
            "overall_result": "Negatived",
            "name_ch": "石禮謙",
            "name_en": "Abraham SHEK",
            "constituency": "Functional",
            "vote": "Abstain",
            "display_order": 10
        },
        {
            "id": 116005,
            "start_date": "2014-01-22T00:00:00",
            "type": "Council Meeting",
            "term_no": 5,
            "vote_number": 7,
            "vote_date": "2014-01-23T00:00:00",
            "vote_time": "2014-01-23T00:25:11",
            "motion_ch": "「捍衞編輯採訪獨立自主」議案",
            "motion_en": "MOTION ON \"SAFEGUARDING EDITORIAL INDEPENDENCE AND AUTONOMY\"",
            "mover_ch": "梁家傑",
            "mover_en": "Alan LEONG",
            "mover_type": "Member",
            "vote_separate_mechanism": "Yes",
            "gc_present_count": 31,
            "gc_vote_count": 30,
            "gc_yes_count": 21,
            "gc_no_count": 6,
            "gc_abstain_count": 3,
            "gc_result": "Passed",
            "fc_present_count": 27,
            "fc_vote_count": 27,
            "fc_yes_count": 14,
            "fc_no_count": 5,
            "fc_abstain_count": 8,
            "fc_result": "Passed",
            "overall_present_count": null,
            "overall_vote_count": null,
            "overall_yes_count": null,
            "overall_no_count": null,
            "overall_abstain_count": null,
            "overall_result": "Passed",
            "name_ch": "石禮謙",
            "name_en": "Abraham SHEK",
            "constituency": "Functional",
            "vote": "Abstain",
            "display_order": 10
        },
        {
            "id": 116705,
            "start_date": "2014-02-19T00:00:00",
            "type": "Council Meeting",
            "term_no": 5,
            "vote_number": 2,
            "vote_date": "2014-02-20T00:00:00",
            "vote_time": "2014-02-20T09:36:53",
            "motion_ch": "《2012年印花稅（修訂）條例草案》－ 二讀",
            "motion_en": "STAMP DUTY (AMENDMENT) BILL 2012 - SECOND READING",
            "mover_ch": "運輸及房屋局局長",
            "mover_en": "Secretary for Transport and Housing",
            "mover_type": "Public Officer",
            "vote_separate_mechanism": "No",
            "gc_present_count": null,
            "gc_vote_count": null,
            "gc_yes_count": null,
            "gc_no_count": null,
            "gc_abstain_count": null,
            "gc_result": null,
            "fc_present_count": null,
            "fc_vote_count": null,
            "fc_yes_count": null,
            "fc_no_count": null,
            "fc_abstain_count": null,
            "fc_result": null,
            "overall_present_count": 47,
            "overall_vote_count": 46,
            "overall_yes_count": 37,
            "overall_no_count": 4,
            "overall_abstain_count": 5,
            "overall_result": "Passed",
            "name_ch": "石禮謙",
            "name_en": "Abraham SHEK",
            "constituency": "Functional",
            "vote": "Abstain",
            "display_order": 10
        },
        {
            "id": 117195,
            "start_date": "2014-02-19T00:00:00",
            "type": "Council Meeting",
            "term_no": 5,
            "vote_number": 9,
            "vote_date": "2014-02-20T00:00:00",
            "vote_time": "2014-02-20T21:38:53",
            "motion_ch": "《2012年印花稅（修訂）條例草案》－ 全體委員會審議階段 － 涂謹申議員的第三項就第16條的修正案",
            "motion_en": "STAMP DUTY (AMENDMENT) BILL 2012 - COMMITTEE STAGE - HON JAMES TO'S 3RD AMENDMENT TO CLAUSE 16",
            "mover_ch": "涂謹申",
            "mover_en": "James TO",
            "mover_type": "Member",
            "vote_separate_mechanism": "Yes",
            "gc_present_count": 29,
            "gc_vote_count": 28,
            "gc_yes_count": 6,
            "gc_no_count": 13,
            "gc_abstain_count": 9,
            "gc_result": "Negatived",
            "fc_present_count": 31,
            "fc_vote_count": 31,
            "fc_yes_count": 9,
            "fc_no_count": 14,
            "fc_abstain_count": 8,
            "fc_result": "Negatived",
            "overall_present_count": null,
            "overall_vote_count": null,
            "overall_yes_count": null,
            "overall_no_count": null,
            "overall_abstain_count": null,
            "overall_result": "Negatived",
            "name_ch": "石禮謙",
            "name_en": "Abraham SHEK",
            "constituency": "Functional",
            "vote": "Abstain",
            "display_order": 10
        },
        {
            "id": 117265,
            "start_date": "2014-02-19T00:00:00",
            "type": "Council Meeting",
            "term_no": 5,
            "vote_number": 10,
            "vote_date": "2014-02-20T00:00:00",
            "vote_time": "2014-02-20T21:45:29",
            "motion_ch": "《2012年印花稅（修訂）條例草案》－ 全體委員會審議階段 － 涂謹申議員的第四項就第16條的修正案",
            "motion_en": "STAMP DUTY (AMENDMENT) BILL 2012 - COMMITTEE STAGE - HON JAMES TO'S 4TH AMENDMENT TO CLAUSE 16",
            "mover_ch": "涂謹申",
            "mover_en": "James TO",
            "mover_type": "Member",
            "vote_separate_mechanism": "Yes",
            "gc_present_count": 29,
            "gc_vote_count": 28,
            "gc_yes_count": 5,
            "gc_no_count": 13,
            "gc_abstain_count": 10,
            "gc_result": "Negatived",
            "fc_present_count": 31,
            "fc_vote_count": 31,
            "fc_yes_count": 9,
            "fc_no_count": 14,
            "fc_abstain_count": 8,
            "fc_result": "Negatived",
            "overall_present_count": null,
            "overall_vote_count": null,
            "overall_yes_count": null,
            "overall_no_count": null,
            "overall_abstain_count": null,
            "overall_result": "Negatived",
            "name_ch": "石禮謙",
            "name_en": "Abraham SHEK",
            "constituency": "Functional",
            "vote": "Abstain",
            "display_order": 10
        },
        {
            "id": 117335,
            "start_date": "2014-02-19T00:00:00",
            "type": "Council Meeting",
            "term_no": 5,
            "vote_number": 11,
            "vote_date": "2014-02-20T00:00:00",
            "vote_time": "2014-02-20T21:51:42",
            "motion_ch": "《2012年印花稅（修訂）條例草案》－ 全體委員會審議階段 － 廖長江議員就第16條的修正案",
            "motion_en": "STAMP DUTY (AMENDMENT) BILL 2012 - COMMITTEE STAGE - HON MARTIN LIAO'S AMENDMENT TO CLAUSE 16",
            "mover_ch": "廖長江",
            "mover_en": "Martin LIAO",
            "mover_type": "Member",
            "vote_separate_mechanism": "Yes",
            "gc_present_count": 29,
            "gc_vote_count": 28,
            "gc_yes_count": 15,
            "gc_no_count": 5,
            "gc_abstain_count": 8,
            "gc_result": "Passed",
            "fc_present_count": 31,
            "fc_vote_count": 31,
            "fc_yes_count": 13,
            "fc_no_count": 5,
            "fc_abstain_count": 13,
            "fc_result": "Negatived",
            "overall_present_count": null,
            "overall_vote_count": null,
            "overall_yes_count": null,
            "overall_no_count": null,
            "overall_abstain_count": null,
            "overall_result": "Negatived",
            "name_ch": "石禮謙",
            "name_en": "Abraham SHEK",
            "constituency": "Functional",
            "vote": "Abstain",
            "display_order": 10
        },
        {
            "id": 118665,
            "start_date": "2014-03-19T00:00:00",
            "type": "Council Meeting",
            "term_no": 5,
            "vote_number": 9,
            "vote_date": "2014-03-21T00:00:00",
            "vote_time": "2014-03-21T18:36:40",
            "motion_ch": "單仲偕議員對鍾國斌議員的「鼓勵工業界回流發展，令本港產業更多元化」議案作出的修正案",
            "motion_en": "AMENDMENT BY HON SIN CHUNG-KAI TO HON CHUNG KWOK-PAN'S MOTION ON \"ENCOURAGING THE RETURN OF THE INDUSTRIAL SECTOR FOR DEVELOPMENT TO MAKE HONG KONG’S INDUSTRIES MORE DIVERSIFIED\"",
            "mover_ch": "單仲偕",
            "mover_en": "SIN Chung-kai",
            "mover_type": "Member",
            "vote_separate_mechanism": "Yes",
            "gc_present_count": 22,
            "gc_vote_count": 21,
            "gc_yes_count": 20,
            "gc_no_count": 0,
            "gc_abstain_count": 1,
            "gc_result": "Passed",
            "fc_present_count": 24,
            "fc_vote_count": 24,
            "fc_yes_count": 23,
            "fc_no_count": 0,
            "fc_abstain_count": 1,
            "fc_result": "Passed",
            "overall_present_count": null,
            "overall_vote_count": null,
            "overall_yes_count": null,
            "overall_no_count": null,
            "overall_abstain_count": null,
            "overall_result": "Passed",
            "name_ch": "石禮謙",
            "name_en": "Abraham SHEK",
            "constituency": "Functional",
            "vote": "Abstain",
            "display_order": 10
        },
        {
            "id": 119155,
            "start_date": "2014-03-26T00:00:00",
            "type": "Council Meeting",
            "term_no": 5,
            "vote_number": 7,
            "vote_date": "2014-03-27T00:00:00",
            "vote_time": "2014-03-27T17:03:33",
            "motion_ch": "田北俊議員對譚耀宗議員就「妥善處理跨境學童引伸的問題」所提，經葉建源議員修正的議案，作出的修正案",
            "motion_en": "AMENDMENT BY HON JAMES TIEN TO HON TAM YIU-CHUNG'S MOTION ON \"PROPERLY DEALING WITH PROBLEMS ARISING FROM CROSS-BOUNDARY STUDENTS\" AS AMENDED BY HON IP KIN-YUEN",
            "mover_ch": "田北俊",
            "mover_en": "James TIEN",
            "mover_type": "Member",
            "vote_separate_mechanism": "Yes",
            "gc_present_count": 29,
            "gc_vote_count": 28,
            "gc_yes_count": 16,
            "gc_no_count": 11,
            "gc_abstain_count": 1,
            "gc_result": "Passed",
            "fc_present_count": 27,
            "fc_vote_count": 27,
            "fc_yes_count": 16,
            "fc_no_count": 6,
            "fc_abstain_count": 5,
            "fc_result": "Passed",
            "overall_present_count": null,
            "overall_vote_count": null,
            "overall_yes_count": null,
            "overall_no_count": null,
            "overall_abstain_count": null,
            "overall_result": "Passed",
            "name_ch": "石禮謙",
            "name_en": "Abraham SHEK",
            "constituency": "Functional",
            "vote": "Abstain",
            "display_order": 10
        },
        {
            "id": 220503,
            "start_date": "2014-01-08T00:00:00",
            "type": "Council Meeting",
            "term_no": 5,
            "vote_number": 3,
            "vote_date": "2014-01-08T00:00:00",
            "vote_time": "2014-01-08T19:24:31",
            "motion_ch": "麥美娟議員對黃定光議員就「推動落馬洲及大嶼山的經濟發展」所提，經盧偉國議員／郭家麒議員修正的議案，作出的修正案",
            "motion_en": "AMENDMENT BY HON ALICE MAK TO HON WONG TING-KWONG'S MOTION ON \"PROMOTING THE ECONOMIC DEVELOPMENT OF LOK MA CHAU AND LANTAU ISLAND\" AS AMENDED BY IR DR HON LO WAI-KWOK / DR HON KWOK KA-KI",
            "mover_ch": "麥美娟",
            "mover_en": "Alice MAK",
            "mover_type": "Member",
            "vote_separate_mechanism": "Yes",
            "gc_present_count": 28,
            "gc_vote_count": 27,
            "gc_yes_count": 21,
            "gc_no_count": 3,
            "gc_abstain_count": 3,
            "gc_result": "Passed",
            "fc_present_count": 30,
            "fc_vote_count": 30,
            "fc_yes_count": 23,
            "fc_no_count": 0,
            "fc_abstain_count": 7,
            "fc_result": "Passed",
            "overall_present_count": null,
            "overall_vote_count": null,
            "overall_yes_count": null,
            "overall_no_count": null,
            "overall_abstain_count": null,
            "overall_result": "Passed",
            "name_ch": "石禮謙",
            "name_en": "Abraham SHEK",
            "constituency": "Functional",
            "vote": "Abstain",
            "display_order": 10
        },
        {
            "id": 220713,
            "start_date": "2014-01-08T00:00:00",
            "type": "Council Meeting",
            "term_no": 5,
            "vote_number": 6,
            "vote_date": "2014-01-09T00:00:00",
            "vote_time": "2014-01-09T16:59:04",
            "motion_ch": "梁繼昌議員對蔣麗芸議員的「全方位協助青年人發展」議案作出的修正案",
            "motion_en": "AMENDMENT BY HON KENNETH LEUNG TO DR HON CHIANG LAI-WAN'S MOTION ON \"ASSISTING YOUNG PEOPLE IN THEIR DEVELOPMENT ON ALL FRONTS\"",
            "mover_ch": "梁繼昌",
            "mover_en": "Kenneth LEUNG",
            "mover_type": "Member",
            "vote_separate_mechanism": "Yes",
            "gc_present_count": 24,
            "gc_vote_count": 23,
            "gc_yes_count": 18,
            "gc_no_count": 0,
            "gc_abstain_count": 5,
            "gc_result": "Passed",
            "fc_present_count": 26,
            "fc_vote_count": 26,
            "fc_yes_count": 18,
            "fc_no_count": 0,
            "fc_abstain_count": 8,
            "fc_result": "Passed",
            "overall_present_count": null,
            "overall_vote_count": null,
            "overall_yes_count": null,
            "overall_no_count": null,
            "overall_abstain_count": null,
            "overall_result": "Passed",
            "name_ch": "石禮謙",
            "name_en": "Abraham SHEK",
            "constituency": "Functional",
            "vote": "Abstain",
            "display_order": 10
        },
        {
            "id": 220923,
            "start_date": "2014-01-08T00:00:00",
            "type": "Council Meeting",
            "term_no": 5,
            "vote_number": 9,
            "vote_date": "2014-01-09T00:00:00",
            "vote_time": "2014-01-09T17:07:45",
            "motion_ch": "黃碧雲議員對蔣麗芸議員就「全方位協助青年人發展」所提，經梁繼昌議員／郭偉强議員／張國柱議員／陳健波議員修正的議案，作出的修正案",
            "motion_en": "AMENDMENT BY DR HON HELENA WONG TO DR HON CHIANG LAI-WAN'S MOTION ON \"ASSISTING YOUNG PEOPLE IN THEIR DEVELOPMENT ON ALL FRONTS\" AS AMENDED BY HON KENNETH LEUNG / HON KWOK WAI-KEUNG / HON CHEUNG KWOK-CHE / HON CHAN KIN-POR",
            "mover_ch": "黃碧雲",
            "mover_en": "Dr Helena WONG",
            "mover_type": "Member",
            "vote_separate_mechanism": "Yes",
            "gc_present_count": 24,
            "gc_vote_count": 23,
            "gc_yes_count": 10,
            "gc_no_count": 4,
            "gc_abstain_count": 9,
            "gc_result": "Negatived",
            "fc_present_count": 26,
            "fc_vote_count": 26,
            "fc_yes_count": 7,
            "fc_no_count": 8,
            "fc_abstain_count": 11,
            "fc_result": "Negatived",
            "overall_present_count": null,
            "overall_vote_count": null,
            "overall_yes_count": null,
            "overall_no_count": null,
            "overall_abstain_count": null,
            "overall_result": "Negatived",
            "name_ch": "石禮謙",
            "name_en": "Abraham SHEK",
            "constituency": "Functional",
            "vote": "Abstain",
            "display_order": 10
        },
        {
            "id": 232152,
            "start_date": "2014-07-09T00:00:00",
            "type": "Council Meeting",
            "term_no": 5,
            "vote_number": 39,
            "vote_date": "2014-07-14T00:00:00",
            "vote_time": "2014-07-14T19:01:58",
            "motion_ch": "《2013年印花稅（修訂）條例草案》－ 全體委員會審議階段 － 涂謹申議員的第二項就第9條的修正案",
            "motion_en": "STAMP DUTY (AMENDMENT) BILL 2013 - COMMITTEE STAGE - HON JAMES TO’S 2ND AMENDMENT TO CLAUSE 9",
            "mover_ch": "涂謹申",
            "mover_en": "James TO",
            "mover_type": "Member",
            "vote_separate_mechanism": "Yes",
            "gc_present_count": 28,
            "gc_vote_count": 27,
            "gc_yes_count": 14,
            "gc_no_count": 11,
            "gc_abstain_count": 2,
            "gc_result": "Negatived",
            "fc_present_count": 25,
            "fc_vote_count": 25,
            "fc_yes_count": 8,
            "fc_no_count": 14,
            "fc_abstain_count": 3,
            "fc_result": "Negatived",
            "overall_present_count": null,
            "overall_vote_count": null,
            "overall_yes_count": null,
            "overall_no_count": null,
            "overall_abstain_count": null,
            "overall_result": "Negatived",
            "name_ch": "石禮謙",
            "name_en": "Abraham SHEK",
            "constituency": "Functional",
            "vote": "Abstain",
            "display_order": 10
        },
        {
            "id": 438405,
            "start_date": "2015-07-08T00:00:00",
            "type": "Council Meeting",
            "term_no": 5,
            "vote_number": 6,
            "vote_date": "2015-07-13T00:00:00",
            "vote_time": "2015-07-13T23:28:54",
            "motion_ch": "「毋忘六四」議案",
            "motion_en": "MOTION ON “NOT FORGETTING THE 4 JUNE INCIDENT”",
            "mover_ch": "單仲偕",
            "mover_en": "SIN Chung-kai",
            "mover_type": "Member",
            "vote_separate_mechanism": "Yes",
            "gc_present_count": 28,
            "gc_vote_count": 27,
            "gc_yes_count": 15,
            "gc_no_count": 12,
            "gc_abstain_count": 0,
            "gc_result": "Passed",
            "fc_present_count": 29,
            "fc_vote_count": 29,
            "fc_yes_count": 8,
            "fc_no_count": 14,
            "fc_abstain_count": 7,
            "fc_result": "Negatived",
            "overall_present_count": null,
            "overall_vote_count": null,
            "overall_yes_count": null,
            "overall_no_count": null,
            "overall_abstain_count": null,
            "overall_result": "Negatived",
            "name_ch": "石禮謙",
            "name_en": "Abraham SHEK",
            "constituency": "Functional",
            "vote": "Abstain",
            "display_order": 10
        },
        {
            "id": 439852,
            "start_date": "2012-10-19T00:00:00",
            "type": "House Committee",
            "term_no": 5,
            "vote_number": 6,
            "vote_date": "2012-10-19T00:00:00",
            "vote_time": "2012-10-19T15:33:29",
            "motion_ch": "選舉7名議員以便任命為政府帳目委員會委員 -何秀蘭議員\n",
            "motion_en": "Election of 7 Members for appointment to the Public Accounts Committee - Hon Cyd HO Sau-lan",
            "mover_ch": null,
            "mover_en": null,
            "mover_type": null,
            "vote_separate_mechanism": "No",
            "gc_present_count": null,
            "gc_vote_count": null,
            "gc_yes_count": null,
            "gc_no_count": null,
            "gc_abstain_count": null,
            "gc_result": null,
            "fc_present_count": null,
            "fc_vote_count": null,
            "fc_yes_count": null,
            "fc_no_count": null,
            "fc_abstain_count": null,
            "fc_result": null,
            "overall_present_count": 40,
            "overall_vote_count": 33,
            "overall_yes_count": 25,
            "overall_no_count": 1,
            "overall_abstain_count": 7,
            "overall_result": "Passed",
            "name_ch": "石禮謙",
            "name_en": "Abraham SHEK",
            "constituency": "Functional",
            "vote": "Abstain",
            "display_order": 10
        },
        {
            "id": 461617,
            "start_date": "2015-11-25T00:00:00",
            "type": "Council Meeting",
            "term_no": 5,
            "vote_number": 6,
            "vote_date": "2015-11-25T00:00:00",
            "vote_time": "2015-11-25T19:16:20",
            "motion_ch": "「盡快取消小學三年級的全港性系統評估」議案",
            "motion_en": "MOTION ON “EXPEDITIOUSLY ABOLISHING THE PRIMARY 3 TERRITORY-WIDE SYSTEM ASSESSMENT”",
            "mover_ch": "陳偉業",
            "mover_en": "Albert CHAN",
            "mover_type": "Member",
            "vote_separate_mechanism": "Yes",
            "gc_present_count": 26,
            "gc_vote_count": 25,
            "gc_yes_count": 17,
            "gc_no_count": 5,
            "gc_abstain_count": 3,
            "gc_result": "Passed",
            "fc_present_count": 25,
            "fc_vote_count": 25,
            "fc_yes_count": 9,
            "fc_no_count": 8,
            "fc_abstain_count": 8,
            "fc_result": "Negatived",
            "overall_present_count": null,
            "overall_vote_count": null,
            "overall_yes_count": null,
            "overall_no_count": null,
            "overall_abstain_count": null,
            "overall_result": "Negatived",
            "name_ch": "石禮謙",
            "name_en": "Abraham SHEK",
            "constituency": "Functional",
            "vote": "Abstain",
            "display_order": 10
        },
        {
            "id": 530588,
            "start_date": "2016-12-07T00:00:00",
            "type": "Council Meeting",
            "term_no": 6,
            "vote_number": 5,
            "vote_date": "2016-12-07T00:00:00",
            "vote_time": "2016-12-07T19:34:56",
            "motion_ch": "姚松炎議員對謝偉俊議員的「制訂房屋政策　紓緩殷切住屋需求」議案作出的修正案",
            "motion_en": "AMENDMENT BY DR HON YIU CHUNG-YIM TO HON PAUL TSE'S MOTION ON “FORMULATING A HOUSING POLICY TO ALLEVIATE THE KEEN HOUSING DEMAND”",
            "mover_ch": "姚松炎",
            "mover_en": "Dr YIU Chung-yim",
            "mover_type": "Member",
            "vote_separate_mechanism": "Yes",
            "gc_present_count": 32,
            "gc_vote_count": 32,
            "gc_yes_count": 13,
            "gc_no_count": 4,
            "gc_abstain_count": 15,
            "gc_result": "Negatived",
            "fc_present_count": 29,
            "fc_vote_count": 28,
            "fc_yes_count": 7,
            "fc_no_count": 6,
            "fc_abstain_count": 15,
            "fc_result": "Negatived",
            "overall_present_count": null,
            "overall_vote_count": null,
            "overall_yes_count": null,
            "overall_no_count": null,
            "overall_abstain_count": null,
            "overall_result": "Negatived",
            "name_ch": "石禮謙",
            "name_en": "Abraham SHEK",
            "constituency": "Functional",
            "vote": "Abstain",
            "display_order": 4
        },
        {
            "id": 590103,
            "start_date": "2017-05-17T00:00:00",
            "type": "Council Meeting",
            "term_no": 6,
            "vote_number": 136,
            "vote_date": "2017-05-18T00:00:00",
            "vote_time": "2017-05-18T09:37:36",
            "motion_ch": "《2017年撥款條例草案》 - 全體委員會審議階段 - 總目156的修正案 (修正案編號153)",
            "motion_en": "APPROPRIATION BILL 2017 - COMMITTEE STAGE - AMENDMENT TO HEAD 156 (AMENDMENT NO. 153)",
            "mover_ch": "葉建源",
            "mover_en": "IP Kin-yuen",
            "mover_type": "Member",
            "vote_separate_mechanism": "Yes",
            "gc_present_count": 24,
            "gc_vote_count": 24,
            "gc_yes_count": 11,
            "gc_no_count": 13,
            "gc_abstain_count": 0,
            "gc_result": "Negatived",
            "fc_present_count": 23,
            "fc_vote_count": 22,
            "fc_yes_count": 2,
            "fc_no_count": 19,
            "fc_abstain_count": 1,
            "fc_result": "Negatived",
            "overall_present_count": null,
            "overall_vote_count": null,
            "overall_yes_count": null,
            "overall_no_count": null,
            "overall_abstain_count": null,
            "overall_result": "Negatived",
            "name_ch": "石禮謙",
            "name_en": "Abraham SHEK",
            "constituency": "Functional",
            "vote": "Abstain",
            "display_order": 4
        },
        {
            "id": 603082,
            "start_date": "2017-06-21T00:00:00",
            "type": "Council Meeting",
            "term_no": 6,
            "vote_number": 1,
            "vote_date": "2017-06-21T00:00:00",
            "vote_time": "2017-06-21T16:24:48",
            "motion_ch": "《2017年稅務(修訂)(第2號)條例草案》 - 二讀",
            "motion_en": "INLAND REVENUE (AMENDMENT) (NO. 2) BILL 2017 - SECOND READING",
            "mover_ch": "運輸及房屋局局長",
            "mover_en": "Secretary for Transport and Housing",
            "mover_type": "Public Officer",
            "vote_separate_mechanism": "No",
            "gc_present_count": null,
            "gc_vote_count": null,
            "gc_yes_count": null,
            "gc_no_count": null,
            "gc_abstain_count": null,
            "gc_result": null,
            "fc_present_count": null,
            "fc_vote_count": null,
            "fc_yes_count": null,
            "fc_no_count": null,
            "fc_abstain_count": null,
            "fc_result": null,
            "overall_present_count": 56,
            "overall_vote_count": 54,
            "overall_yes_count": 43,
            "overall_no_count": 9,
            "overall_abstain_count": 2,
            "overall_result": "Passed",
            "name_ch": "石禮謙",
            "name_en": "Abraham SHEK",
            "constituency": "Functional",
            "vote": "Abstain",
            "display_order": 4
        },
        {
            "id": 613687,
            "start_date": "2017-07-19T00:00:00",
            "type": "Finance Committee",
            "term_no": 6,
            "vote_number": 1,
            "vote_date": "2017-07-19T00:00:00",
            "vote_time": "2017-07-19T16:45:10",
            "motion_ch": "本委員會同意處理委員根據《財務委員會會議程序》第37A段擬動議的議案(編號：0002)",
            "motion_en": "That this Committee should proceed with the motion proposed to be moved by a member under paragraph 37A of the Finance Committee Procedure(No.: 0002)",
            "mover_ch": "",
            "mover_en": "",
            "mover_type": "Public Officer",
            "vote_separate_mechanism": "No",
            "gc_present_count": null,
            "gc_vote_count": null,
            "gc_yes_count": null,
            "gc_no_count": null,
            "gc_abstain_count": null,
            "gc_result": null,
            "fc_present_count": null,
            "fc_vote_count": null,
            "fc_yes_count": null,
            "fc_no_count": null,
            "fc_abstain_count": null,
            "fc_result": null,
            "overall_present_count": 32,
            "overall_vote_count": 29,
            "overall_yes_count": 20,
            "overall_no_count": 6,
            "overall_abstain_count": 3,
            "overall_result": "Passed",
            "name_ch": "石禮謙",
            "name_en": "Abraham SHEK",
            "constituency": "Functional",
            "vote": "Abstain",
            "display_order": 4
        },
        {
            "id": 614191,
            "start_date": "2017-07-19T00:00:00",
            "type": "Finance Committee",
            "term_no": 6,
            "vote_number": 9,
            "vote_date": "2017-07-19T00:00:00",
            "vote_time": "2017-07-19T17:14:48",
            "motion_ch": "本委員會同意處理委員根據《財務委員會會議程序》第37A段擬動議的議案(編號：0026)",
            "motion_en": "That this Committee should proceed with the motion proposed to be moved by a member under paragraph 37A of the Finance Committee Procedure (No.: 0026)",
            "mover_ch": "",
            "mover_en": "",
            "mover_type": "Public Officer",
            "vote_separate_mechanism": "No",
            "gc_present_count": null,
            "gc_vote_count": null,
            "gc_yes_count": null,
            "gc_no_count": null,
            "gc_abstain_count": null,
            "gc_result": null,
            "fc_present_count": null,
            "fc_vote_count": null,
            "fc_yes_count": null,
            "fc_no_count": null,
            "fc_abstain_count": null,
            "fc_result": null,
            "overall_present_count": 41,
            "overall_vote_count": 39,
            "overall_yes_count": 20,
            "overall_no_count": 18,
            "overall_abstain_count": 1,
            "overall_result": "Passed",
            "name_ch": "石禮謙",
            "name_en": "Abraham SHEK",
            "constituency": "Functional",
            "vote": "Abstain",
            "display_order": 4
        },
        {
            "id": 635603,
            "start_date": "2018-01-10T00:00:00",
            "type": "Council Meeting",
            "term_no": 6,
            "vote_number": 7,
            "vote_date": "2018-01-11T00:00:00",
            "vote_time": "2018-01-11T19:02:54",
            "motion_ch": "《2017年印花稅(修訂)條例草案》 - 全體委員會審議 - 涂謹申議員的第二組修正案 - 第5及7條",
            "motion_en": "STAMP DUTY (AMENDMENT) BILL 2017 - CONSIDERATION BY COMMITTEE OF THE WHOLE COUNCIL - HON JAMES TO’S SECOND GROUP OF AMENDMENTS - CLAUSES 5 AND 7",
            "mover_ch": "涂謹申",
            "mover_en": "James TO",
            "mover_type": "Member",
            "vote_separate_mechanism": "Yes",
            "gc_present_count": 22,
            "gc_vote_count": 22,
            "gc_yes_count": 11,
            "gc_no_count": 0,
            "gc_abstain_count": 11,
            "gc_result": "Negatived",
            "fc_present_count": 28,
            "fc_vote_count": 27,
            "fc_yes_count": 9,
            "fc_no_count": 0,
            "fc_abstain_count": 18,
            "fc_result": "Negatived",
            "overall_present_count": null,
            "overall_vote_count": null,
            "overall_yes_count": null,
            "overall_no_count": null,
            "overall_abstain_count": null,
            "overall_result": "Negatived",
            "name_ch": "石禮謙",
            "name_en": "Abraham SHEK",
            "constituency": "Functional",
            "vote": "Abstain",
            "display_order": 4
        },
        {
            "id": 689677,
            "start_date": "2018-07-04T00:00:00",
            "type": "Council Meeting",
            "term_no": 6,
            "vote_number": 3,
            "vote_date": "2018-07-05T00:00:00",
            "vote_time": "2018-07-05T13:36:54",
            "motion_ch": "許智峯議員對盧偉國議員就「加快推動智慧城市發展」所提，經張華峰議員、謝偉銓議員、楊岳橋議員及葛珮帆議員修正的議案，作出的修正案",
            "motion_en": "AMENDMENT BY HON HUI CHI-FUNG TO IR DR HON LO WAI-KWOK'S MOTION ON “EXPEDITING THE PROMOTION OF SMART CITY DEVELOPMENT” AS AMENDED BY HON CHRISTOPHER CHEUNG, HON TONY TSE, HON ALVIN YEUNG AND DR HON ELIZABETH QUAT",
            "mover_ch": "許智峯",
            "mover_en": "HUI Chi-fung",
            "mover_type": "Member",
            "vote_separate_mechanism": "Yes",
            "gc_present_count": 24,
            "gc_vote_count": 24,
            "gc_yes_count": 16,
            "gc_no_count": 1,
            "gc_abstain_count": 7,
            "gc_result": "Passed",
            "fc_present_count": 25,
            "fc_vote_count": 24,
            "fc_yes_count": 7,
            "fc_no_count": 4,
            "fc_abstain_count": 13,
            "fc_result": "Negatived",
            "overall_present_count": null,
            "overall_vote_count": null,
            "overall_yes_count": null,
            "overall_no_count": null,
            "overall_abstain_count": null,
            "overall_result": "Negatived",
            "name_ch": "石禮謙",
            "name_en": "Abraham SHEK",
            "constituency": "Functional",
            "vote": "Abstain",
            "display_order": 4
        },
        {
            "id": 693239,
            "start_date": "2018-07-06T00:00:00",
            "type": "House Committee",
            "term_no": 6,
            "vote_number": 1,
            "vote_date": "2018-07-06T00:00:00",
            "vote_time": "2018-07-06T15:30:55",
            "motion_ch": "建議於2018年7月11日的立法會會議上動議議案，以尋求立法會授權交通事務委員會，就有關沙田至中環線土瓜灣站和會展站建造工程質量問題行使《立法會(權力及特權)條例》(第 382章)第9(1)條所賦予的權力",
            "motion_en": "Proposal to move a motion at the Council meeting of 11 July 2018 to seek the Council's authorization for the Panel on Transport to exercise the powers conferred by section 9(1) of the Legislative Council (Powers and Privileges) Ordinance (Cap. 382) in respect of the quality of construction works at To Kwa Wan station and Exhibition Centre station of the Shatin to Central Link",
            "mover_ch": "",
            "mover_en": "",
            "mover_type": "Public Officer",
            "vote_separate_mechanism": "No",
            "gc_present_count": null,
            "gc_vote_count": null,
            "gc_yes_count": null,
            "gc_no_count": null,
            "gc_abstain_count": null,
            "gc_result": null,
            "fc_present_count": null,
            "fc_vote_count": null,
            "fc_yes_count": null,
            "fc_no_count": null,
            "fc_abstain_count": null,
            "fc_result": null,
            "overall_present_count": 60,
            "overall_vote_count": 59,
            "overall_yes_count": 24,
            "overall_no_count": 34,
            "overall_abstain_count": 1,
            "overall_result": "Negatived",
            "name_ch": "石禮謙",
            "name_en": "Abraham SHEK",
            "constituency": "Functional",
            "vote": "Abstain",
            "display_order": 4
        },
        {
            "id": 701315,
            "start_date": "2018-11-21T00:00:00",
            "type": "Council Meeting",
            "term_no": 6,
            "vote_number": 1,
            "vote_date": "2018-11-21T00:00:00",
            "vote_time": "2018-11-21T19:06:32",
            "motion_ch": "陳恒鑌議員對田北辰議員的「重整港鐵公司管治」議案作出的修正案",
            "motion_en": "AMENDMENT BY HON CHAN HAN-PAN TO HON MICHAEL TIEN'S MOTION ON “RESTRUCTURING THE GOVERNANCE OF MTR CORPORATION LIMITED”",
            "mover_ch": "陳恒鑌",
            "mover_en": "CHAN Han-pan",
            "mover_type": "Member",
            "vote_separate_mechanism": "Yes",
            "gc_present_count": 28,
            "gc_vote_count": 28,
            "gc_yes_count": 10,
            "gc_no_count": 0,
            "gc_abstain_count": 18,
            "gc_result": "Negatived",
            "fc_present_count": 28,
            "fc_vote_count": 27,
            "fc_yes_count": 8,
            "fc_no_count": 1,
            "fc_abstain_count": 18,
            "fc_result": "Negatived",
            "overall_present_count": null,
            "overall_vote_count": null,
            "overall_yes_count": null,
            "overall_no_count": null,
            "overall_abstain_count": null,
            "overall_result": "Negatived",
            "name_ch": "石禮謙",
            "name_en": "Abraham SHEK",
            "constituency": "Functional",
            "vote": "Abstain",
            "display_order": 4
        },
        {
            "id": 701519,
            "start_date": "2018-11-21T00:00:00",
            "type": "Council Meeting",
            "term_no": 6,
            "vote_number": 4,
            "vote_date": "2018-11-21T00:00:00",
            "vote_time": "2018-11-21T19:13:27",
            "motion_ch": "「重整港鐵公司管治」議案",
            "motion_en": "MOTION ON “RESTRUCTURING THE GOVERNANCE OF MTR CORPORATION LIMITED”",
            "mover_ch": "田北辰",
            "mover_en": "Michael TIEN",
            "mover_type": "Member",
            "vote_separate_mechanism": "Yes",
            "gc_present_count": 28,
            "gc_vote_count": 28,
            "gc_yes_count": 11,
            "gc_no_count": 0,
            "gc_abstain_count": 17,
            "gc_result": "Negatived",
            "fc_present_count": 29,
            "fc_vote_count": 28,
            "fc_yes_count": 10,
            "fc_no_count": 0,
            "fc_abstain_count": 18,
            "fc_result": "Negatived",
            "overall_present_count": null,
            "overall_vote_count": null,
            "overall_yes_count": null,
            "overall_no_count": null,
            "overall_abstain_count": null,
            "overall_result": "Negatived",
            "name_ch": "石禮謙",
            "name_en": "Abraham SHEK",
            "constituency": "Functional",
            "vote": "Abstain",
            "display_order": 4
        },
        {
            "id": 714658,
            "start_date": "2019-02-20T00:00:00",
            "type": "Council Meeting",
            "term_no": 6,
            "vote_number": 1,
            "vote_date": "2019-02-21T00:00:00",
            "vote_time": "2019-02-21T11:54:40",
            "motion_ch": "根據《立法會(權力及特權)條例》動議的議案",
            "motion_en": "MOTION UNDER THE LEGISLATIVE COUNCIL (POWERS AND PRIVILEGES) ORDINANCE",
            "mover_ch": "陳淑莊",
            "mover_en": "Tanya CHAN",
            "mover_type": "Member",
            "vote_separate_mechanism": "Yes",
            "gc_present_count": 31,
            "gc_vote_count": 31,
            "gc_yes_count": 16,
            "gc_no_count": 13,
            "gc_abstain_count": 2,
            "gc_result": "Passed",
            "fc_present_count": 30,
            "fc_vote_count": 29,
            "fc_yes_count": 10,
            "fc_no_count": 17,
            "fc_abstain_count": 2,
            "fc_result": "Negatived",
            "overall_present_count": null,
            "overall_vote_count": null,
            "overall_yes_count": null,
            "overall_no_count": null,
            "overall_abstain_count": null,
            "overall_result": "Negatived",
            "name_ch": "石禮謙",
            "name_en": "Abraham SHEK",
            "constituency": "Functional",
            "vote": "Abstain",
            "display_order": 4
        }
    ]
}
