{
    "odata.metadata": "https://app.legco.gov.hk/BillsDB/odata/$metadata#Vbills",
    "odata.count": "7",
    "value": [
        {
            "internal_key": "06657             ",
            "ordinance_title_eng": "Inland Revenue Ordinance",
            "ordinance_title_chi": "稅務條例",
            "ordinance_content_url_eng": "https://www.elegislation.gov.hk/hk/cap112?_lang=en",
            "ordinance_content_url_chi": "https://www.elegislation.gov.hk/hk/cap112?_lang=zh-Hant-HK",
            "bill_title_eng": "Inland Revenue (Amendment) (No. 7) Bill 2018",
            "bill_title_chi": "2018年稅務(修訂)(第7號)條例草案",
            "proposed_by_eng": "Secretary for Financial Services and the Treasury",
            "proposed_by_chi": "財經事務及庫務局局長",
            "bill_gazette_date": "2018-11-02T00:00:00",
            "bill_content_url_eng": "https://www.legco.gov.hk/yr18-19/english/bills/b201811022.pdf",
            "bill_content_url_chi": "https://www.legco.gov.hk/yr18-19/chinese/bills/b201811022.pdf",
            "bill_gazette_date_2": null,
            "bill_content_url_2_eng": "",
            "bill_content_url_2_chi": "",
            "bill_gazette_date_3": null,
            "bill_content_url_3_eng": "",
            "bill_content_url_3_chi": "",
            "ordinance_gazette_date": "2019-03-01T00:00:00",
            "ordinance_year_number_eng": "Ord. No. 6 of 2019",
            "ordinance_year_number_chi": "2019年第6號條例",
            "ordinace_gazette_content_url_eng": "https://www.legco.gov.hk/yr18-19/english/ord/2019ord006-e.pdf",
            "ordinance_gazette_content_url_chi": "https://www.legco.gov.hk/yr18-19/chinese/ord/2019ord006-c.pdf",
            "legco_brief_file_reference": "TsyB R 00/800/24/0 (C)",
            "legco_brief_url_eng": "http://library.legco.gov.hk:1080/search~S10?/.bills/br/.bills/br/1,1,1,B/l962~bills/br&amp;FF=&amp;1,0,,0,0",
            "legco_brief_url_chi": "http://library.legco.gov.hk:1080/search~S10?/.bills/br/.bills/br/1,1,1,B/l962~bills/br&amp;FF=&amp;1,0,,1,0",
            "first_reading_date": "2018-11-14T00:00:00",
            "first_reading_date_hansard_url_eng": "https://www.legco.gov.hk/yr18-19/english/counmtg/hansard/cm20181114-translate-e.pdf#nameddest=b1r02",
            "first_reading_date_hansard_url_chi": "https://www.legco.gov.hk/yr18-19/chinese/counmtg/hansard/cm20181114-translate-c.pdf#nameddest=b1r02",
            "first_reading_date_2": null,
            "first_reading_date_2_hansard_url_eng": "",
            "first_reading_date_2_hansard_url_chi": "",
            "bills_committee_title_eng": "Bills Committee on Inland Revenue (Amendment) (No. 7) Bill 2018",
            "bills_committee_title_chi": "2018年稅務(修訂)(第7號)條例草案委員會",
            "bills_committee_url_eng": "https://www.legco.gov.hk/yr18-19/english/bc/bc03/general/bc03.htm",
            "bills_committee_url_chi": "https://www.legco.gov.hk/yr18-19/chinese/bc/bc03/general/bc03.htm",
            "bills_committee_formation_date": "2018-11-16T00:00:00",
            "bills_committee_report_url_eng": "https://www.legco.gov.hk/yr18-19/english/bc/bc03/reports/bc0320190220cb1-566-e.pdf",
            "bills_committee_report_url_chi": "https://www.legco.gov.hk/yr18-19/chinese/bc/bc03/reports/bc0320190220cb1-566-c.pdf",
            "second_reading_date": "2019-02-20T00:00:00",
            "second_reading_date_hansard_url_eng": "https://www.legco.gov.hk/yr18-19/english/counmtg/hansard/cm20190220-translate-e.pdf#nameddest=b2d02a",
            "second_reading_date_hansard_url_chi": "https://www.legco.gov.hk/yr18-19/chinese/counmtg/hansard/cm20190220-translate-c.pdf#nameddest=b2d02a",
            "second_reading_date_2": null,
            "second_reading_date_2_hansard_url_eng": "",
            "second_reading_date_2_hansard_url_chi": "",
            "second_reading_date_3": null,
            "second_reading_date_3_hansard_url_eng": "",
            "second_reading_date_3_hansard_url_chi": "",
            "second_reading_date_4": null,
            "second_reading_date_4_hansard_url_eng": "",
            "second_reading_date_4_hansard_url_chi": "",
            "second_reading_date_5": null,
            "second_reading_date_5_hansard_url_eng": "",
            "second_reading_date_5_hansard_url_chi": "",
            "third_reading_date": "2019-02-20T00:00:00",
            "third_reading_date_hansard_url_eng": "https://www.legco.gov.hk/yr18-19/english/counmtg/hansard/cm20190220-translate-e.pdf#nameddest=b3r02a",
            "third_reading_date_hansard_url_chi": "https://www.legco.gov.hk/yr18-19/chinese/counmtg/hansard/cm20190220-translate-c.pdf#nameddest=b3r02a",
            "additional_information_eng": "",
            "additional_information_chi": "",
            "remarks_eng": "",
            "remarks_chi": ""
        },
        {
            "internal_key": "06661             ",
            "ordinance_title_eng": "Inland Revenue Ordinance",
            "ordinance_title_chi": "稅務條例",
            "ordinance_content_url_eng": "https://www.elegislation.gov.hk/hk/cap112?_lang=en",
            "ordinance_content_url_chi": "https://www.elegislation.gov.hk/hk/cap112?_lang=zh-Hant-HK",
            "bill_title_eng": "Inland Revenue and MPF Schemes Legislation (Tax Deductions for Annuity Premiums and MPF Voluntary Contributions) (Amendment) Bill 2018",
            "bill_title_chi": "2018年稅務及強積金計劃法例(關於年金保費及強積金自願性供款的稅務扣除)(修訂)條例草案",
            "proposed_by_eng": "Secretary for Financial Services and the Treasury",
            "proposed_by_chi": "財經事務及庫務局局長",
            "bill_gazette_date": "2018-12-07T00:00:00",
            "bill_content_url_eng": "https://www.legco.gov.hk/yr18-19/english/bills/b201812071.pdf",
            "bill_content_url_chi": "https://www.legco.gov.hk/yr18-19/chinese/bills/b201812071.pdf",
            "bill_gazette_date_2": null,
            "bill_content_url_2_eng": "",
            "bill_content_url_2_chi": "",
            "bill_gazette_date_3": null,
            "bill_content_url_3_eng": "",
            "bill_content_url_3_chi": "",
            "ordinance_gazette_date": "2019-03-29T00:00:00",
            "ordinance_year_number_eng": "Ord. No. 7 of 2019",
            "ordinance_year_number_chi": "2019年第7號條例",
            "ordinace_gazette_content_url_eng": "https://www.legco.gov.hk/yr18-19/english/ord/2019ord007-e.pdf",
            "ordinance_gazette_content_url_chi": "https://www.legco.gov.hk/yr18-19/chinese/ord/2019ord007-c.pdf",
            "legco_brief_file_reference": "INS/2/18C",
            "legco_brief_url_eng": "http://library.legco.gov.hk:1080/search~S10?/.bills/br/.bills/br/1,1,1,B/l962~bills/br&amp;FF=&amp;1,0,,0,0",
            "legco_brief_url_chi": "http://library.legco.gov.hk:1080/search~S10?/.bills/br/.bills/br/1,1,1,B/l962~bills/br&amp;FF=&amp;1,0,,1,0",
            "first_reading_date": "2018-12-12T00:00:00",
            "first_reading_date_hansard_url_eng": "https://www.legco.gov.hk/yr18-19/english/counmtg/hansard/cm20181212-translate-e.pdf#nameddest=b1r01",
            "first_reading_date_hansard_url_chi": "https://www.legco.gov.hk/yr18-19/chinese/counmtg/hansard/cm20181212-translate-c.pdf#nameddest=b1r01",
            "first_reading_date_2": null,
            "first_reading_date_2_hansard_url_eng": "",
            "first_reading_date_2_hansard_url_chi": "",
            "bills_committee_title_eng": "Bills Committee on Inland Revenue and MPF Schemes Legislation (Tax Deductions for Annuity Premiums and MPF Voluntary Contributions) (Amendment) Bill 2018",
            "bills_committee_title_chi": "2018年稅務及強積金計劃法例(關於年金保費及強積金自願性供款的稅務扣除)(修訂)條例草案委員會",
            "bills_committee_url_eng": "https://www.legco.gov.hk/yr18-19/english/bc/bc05/general/bc05.htm",
            "bills_committee_url_chi": "https://www.legco.gov.hk/yr18-19/chinese/bc/bc05/general/bc05.htm",
            "bills_committee_formation_date": "2018-12-14T00:00:00",
            "bills_committee_report_url_eng": "https://www.legco.gov.hk/yr18-19/english/bc/bc05/reports/bc0520190320cb1-693-e.pdf",
            "bills_committee_report_url_chi": "https://www.legco.gov.hk/yr18-19/chinese/bc/bc05/reports/bc0520190320cb1-693-c.pdf",
            "second_reading_date": "2019-03-20T00:00:00",
            "second_reading_date_hansard_url_eng": "https://www.legco.gov.hk/yr18-19/english/counmtg/hansard/cm20190320-translate-e.pdf#nameddest=b2d01a",
            "second_reading_date_hansard_url_chi": "https://www.legco.gov.hk/yr18-19/chinese/counmtg/hansard/cm20190320-translate-c.pdf#nameddest=b2d01a",
            "second_reading_date_2": null,
            "second_reading_date_2_hansard_url_eng": "",
            "second_reading_date_2_hansard_url_chi": "",
            "second_reading_date_3": null,
            "second_reading_date_3_hansard_url_eng": "",
            "second_reading_date_3_hansard_url_chi": "",
            "second_reading_date_4": null,
            "second_reading_date_4_hansard_url_eng": "",
            "second_reading_date_4_hansard_url_chi": "",
            "second_reading_date_5": null,
            "second_reading_date_5_hansard_url_eng": "",
            "second_reading_date_5_hansard_url_chi": "",
            "third_reading_date": "2019-03-20T00:00:00",
            "third_reading_date_hansard_url_eng": "https://www.legco.gov.hk/yr18-19/english/counmtg/hansard/cm20190320-translate-e.pdf#nameddest=b3r01a",
            "third_reading_date_hansard_url_chi": "https://www.legco.gov.hk/yr18-19/chinese/counmtg/hansard/cm20190320-translate-c.pdf#nameddest=b3r01a",
            "additional_information_eng": "",
            "additional_information_chi": "",
            "remarks_eng": "",
            "remarks_chi": ""
        },
        {
            "internal_key": "06662             ",
            "ordinance_title_eng": "Inland Revenue Ordinance",
            "ordinance_title_chi": "稅務條例",
            "ordinance_content_url_eng": "https://www.elegislation.gov.hk/hk/cap112?_lang=en",
            "ordinance_content_url_chi": "https://www.elegislation.gov.hk/hk/cap112?_lang=zh-Hant-HK",
            "bill_title_eng": "Inland Revenue (Profits Tax Exemption for Funds) (Amendment) Bill 2018",
            "bill_title_chi": "2018年稅務(豁免基金繳付利得稅)(修訂)條例草案",
            "proposed_by_eng": "Secretary for Financial Services and the Treasury",
            "proposed_by_chi": "財經事務及庫務局局長",
            "bill_gazette_date": "2018-12-07T00:00:00",
            "bill_content_url_eng": "https://www.legco.gov.hk/yr18-19/english/bills/b201812072.pdf",
            "bill_content_url_chi": "https://www.legco.gov.hk/yr18-19/chinese/bills/b201812072.pdf",
            "bill_gazette_date_2": null,
            "bill_content_url_2_eng": "",
            "bill_content_url_2_chi": "",
            "bill_gazette_date_3": null,
            "bill_content_url_3_eng": "",
            "bill_content_url_3_chi": "",
            "ordinance_gazette_date": "2019-03-01T00:00:00",
            "ordinance_year_number_eng": "Ord. No. 5 of 2019",
            "ordinance_year_number_chi": "2019年第5號條例",
            "ordinace_gazette_content_url_eng": "https://www.legco.gov.hk/yr18-19/english/ord/2019ord005-e.pdf",
            "ordinance_gazette_content_url_chi": "https://www.legco.gov.hk/yr18-19/chinese/ord/2019ord005-c.pdf",
            "legco_brief_file_reference": "ASST/3/1/5C (2018) Pt.19",
            "legco_brief_url_eng": "http://library.legco.gov.hk:1080/search~S10?/.bills/br/.bills/br/1,1,1,B/l962~bills/br&amp;FF=&amp;1,0,,0,0",
            "legco_brief_url_chi": "http://library.legco.gov.hk:1080/search~S10?/.bills/br/.bills/br/1,1,1,B/l962~bills/br&amp;FF=&amp;1,0,,1,0",
            "first_reading_date": "2018-12-12T00:00:00",
            "first_reading_date_hansard_url_eng": "https://www.legco.gov.hk/yr18-19/english/counmtg/hansard/cm20181212-translate-e.pdf#nameddest=b1r02",
            "first_reading_date_hansard_url_chi": "https://www.legco.gov.hk/yr18-19/chinese/counmtg/hansard/cm20181212-translate-c.pdf#nameddest=b1r02",
            "first_reading_date_2": null,
            "first_reading_date_2_hansard_url_eng": "",
            "first_reading_date_2_hansard_url_chi": "",
            "bills_committee_title_eng": "Bills Committee on Inland Revenue (Profits Tax Exemption for Funds) (Amendment) Bill 2018",
            "bills_committee_title_chi": "2018年稅務(豁免基金繳付利得稅)(修訂)條例草案委員會",
            "bills_committee_url_eng": "https://www.legco.gov.hk/yr18-19/english/bc/bc06/general/bc06.htm",
            "bills_committee_url_chi": "https://www.legco.gov.hk/yr18-19/chinese/bc/bc06/general/bc06.htm",
            "bills_committee_formation_date": "2018-12-14T00:00:00",
            "bills_committee_report_url_eng": "https://www.legco.gov.hk/yr18-19/english/bc/bc06/reports/bc0620190220cb1-565-e.pdf",
            "bills_committee_report_url_chi": "https://www.legco.gov.hk/yr18-19/chinese/bc/bc06/reports/bc0620190220cb1-565-c.pdf",
            "second_reading_date": "2019-02-20T00:00:00",
            "second_reading_date_hansard_url_eng": "https://www.legco.gov.hk/yr18-19/english/counmtg/hansard/cm20190220-translate-e.pdf#nameddest=b2d01a",
            "second_reading_date_hansard_url_chi": "https://www.legco.gov.hk/yr18-19/chinese/counmtg/hansard/cm20190220-translate-c.pdf#nameddest=b2d01a",
            "second_reading_date_2": null,
            "second_reading_date_2_hansard_url_eng": "",
            "second_reading_date_2_hansard_url_chi": "",
            "second_reading_date_3": null,
            "second_reading_date_3_hansard_url_eng": "",
            "second_reading_date_3_hansard_url_chi": "",
            "second_reading_date_4": null,
            "second_reading_date_4_hansard_url_eng": "",
            "second_reading_date_4_hansard_url_chi": "",
            "second_reading_date_5": null,
            "second_reading_date_5_hansard_url_eng": "",
            "second_reading_date_5_hansard_url_chi": "",
            "third_reading_date": "2019-02-20T00:00:00",
            "third_reading_date_hansard_url_eng": "https://www.legco.gov.hk/yr18-19/english/counmtg/hansard/cm20190220-translate-e.pdf#nameddest=b3r01a",
            "third_reading_date_hansard_url_chi": "https://www.legco.gov.hk/yr18-19/chinese/counmtg/hansard/cm20190220-translate-c.pdf#nameddest=b3r01a",
            "additional_information_eng": "",
            "additional_information_chi": "",
            "remarks_eng": "",
            "remarks_chi": ""
        },
        {
            "internal_key": "06669             ",
            "ordinance_title_eng": "Appropriation",
            "ordinance_title_chi": "撥款",
            "ordinance_content_url_eng": "",
            "ordinance_content_url_chi": "",
            "bill_title_eng": "Appropriation Bill 2019",
            "bill_title_chi": "2019年撥款條例草案",
            "proposed_by_eng": "Financial Secretary",
            "proposed_by_chi": "財政司司長",
            "bill_gazette_date": "2019-02-27T00:00:00",
            "bill_content_url_eng": "https://www.legco.gov.hk/yr18-19/english/bills/b201902271.pdf",
            "bill_content_url_chi": "https://www.legco.gov.hk/yr18-19/chinese/bills/b201902271.pdf",
            "bill_gazette_date_2": null,
            "bill_content_url_2_eng": "",
            "bill_content_url_2_chi": "",
            "bill_gazette_date_3": null,
            "bill_content_url_3_eng": "",
            "bill_content_url_3_chi": "",
            "ordinance_gazette_date": "2019-05-24T00:00:00",
            "ordinance_year_number_eng": "Ord. No. 8 of 2019",
            "ordinance_year_number_chi": "2019年第8號條例",
            "ordinace_gazette_content_url_eng": "https://www.legco.gov.hk/yr18-19/english/ord/2019ord008-e.pdf",
            "ordinance_gazette_content_url_chi": "https://www.legco.gov.hk/yr18-19/chinese/ord/2019ord008-c.pdf",
            "legco_brief_file_reference": "",
            "legco_brief_url_eng": "",
            "legco_brief_url_chi": "",
            "first_reading_date": "2019-02-27T00:00:00",
            "first_reading_date_hansard_url_eng": "https://www.legco.gov.hk/yr18-19/english/counmtg/hansard/cm20190227-translate-e.pdf#nameddest=b1r01",
            "first_reading_date_hansard_url_chi": "https://www.legco.gov.hk/yr18-19/chinese/counmtg/hansard/cm20190227-translate-c.pdf#nameddest=b1r01",
            "first_reading_date_2": null,
            "first_reading_date_2_hansard_url_eng": "",
            "first_reading_date_2_hansard_url_chi": "",
            "bills_committee_title_eng": "",
            "bills_committee_title_chi": "",
            "bills_committee_url_eng": "",
            "bills_committee_url_chi": "",
            "bills_committee_formation_date": null,
            "bills_committee_report_url_eng": "",
            "bills_committee_report_url_chi": "",
            "second_reading_date": "2019-04-17T00:00:00",
            "second_reading_date_hansard_url_eng": "https://www.legco.gov.hk/yr18-19/english/counmtg/hansard/cm20190417-translate-e.pdf#nameddest=b2d01a",
            "second_reading_date_hansard_url_chi": "https://www.legco.gov.hk/yr18-19/chinese/counmtg/hansard/cm20190417-translate-c.pdf#nameddest=b2d01a",
            "second_reading_date_2": "2019-04-18T00:00:00",
            "second_reading_date_2_hansard_url_eng": "https://www.legco.gov.hk/yr18-19/english/counmtg/hansard/cm20190418-translate-e.pdf#nameddest=b2d01a",
            "second_reading_date_2_hansard_url_chi": "https://www.legco.gov.hk/yr18-19/chinese/counmtg/hansard/cm20190418-translate-c.pdf#nameddest=b2d01a",
            "second_reading_date_3": "2019-05-08T00:00:00",
            "second_reading_date_3_hansard_url_eng": "https://www.legco.gov.hk/yr18-19/english/counmtg/hansard/cm20190508-translate-e.pdf#nameddest=b2d01a",
            "second_reading_date_3_hansard_url_chi": "https://www.legco.gov.hk/yr18-19/chinese/counmtg/hansard/cm20190508-translate-c.pdf#nameddest=b2d01a",
            "second_reading_date_4": "2019-05-09T00:00:00",
            "second_reading_date_4_hansard_url_eng": "https://www.legco.gov.hk/yr18-19/english/counmtg/hansard/cm20190509-translate-e.pdf#nameddest=cwc01a",
            "second_reading_date_4_hansard_url_chi": "https://www.legco.gov.hk/yr18-19/chinese/counmtg/hansard/cm20190509-translate-c.pdf#nameddest=cwc01a",
            "second_reading_date_5": "2019-05-15T00:00:00",
            "second_reading_date_5_hansard_url_eng": "https://www.legco.gov.hk/yr18-19/english/counmtg/hansard/cm20190515-translate-e.pdf#nameddest=cwc01a",
            "second_reading_date_5_hansard_url_chi": "https://www.legco.gov.hk/yr18-19/chinese/counmtg/hansard/cm20190515-translate-c.pdf#nameddest=cwc01a",
            "third_reading_date": "2019-05-16T00:00:00",
            "third_reading_date_hansard_url_eng": "https://www.legco.gov.hk/yr18-19/english/counmtg/hansard/cm20190516-translate-e.pdf#nameddest=b3r01a",
            "third_reading_date_hansard_url_chi": "https://www.legco.gov.hk/yr18-19/chinese/counmtg/hansard/cm20190516-translate-c.pdf#nameddest=b3r01a",
            "additional_information_eng": "",
            "additional_information_chi": "",
            "remarks_eng": "Read Hansard of 16 May 2019 for Second Reading",
            "remarks_chi": "二讀請參閱2019年5月16日的會議紀錄"
        },
        {
            "internal_key": "06672             ",
            "ordinance_title_eng": "High Court Ordinance",
            "ordinance_title_chi": "高等法院條例",
            "ordinance_content_url_eng": "https://www.elegislation.gov.hk/hk/cap4?_lang=en",
            "ordinance_content_url_chi": "https://www.elegislation.gov.hk/hk/cap4?_lang=zh-Hant-HK",
            "bill_title_eng": "Judicial Officers (Extension of Retirement Age) (Amendment) Bill 2019",
            "bill_title_chi": "2019年司法人員(延展退休年齡)(修訂)條例草案",
            "proposed_by_eng": "Chief Secretary for Administration",
            "proposed_by_chi": "政務司司長",
            "bill_gazette_date": "2019-03-01T00:00:00",
            "bill_content_url_eng": "https://www.legco.gov.hk/yr18-19/english/bills/b201903011.pdf",
            "bill_content_url_chi": "https://www.legco.gov.hk/yr18-19/chinese/bills/b201903011.pdf",
            "bill_gazette_date_2": null,
            "bill_content_url_2_eng": "",
            "bill_content_url_2_chi": "",
            "bill_gazette_date_3": null,
            "bill_content_url_3_eng": "",
            "bill_content_url_3_chi": "",
            "ordinance_gazette_date": "2019-12-06T00:00:00",
            "ordinance_year_number_eng": "Ord. No. 10 of 2019",
            "ordinance_year_number_chi": "2019年第10號條例",
            "ordinace_gazette_content_url_eng": "https://www.legco.gov.hk/yr19-20/english/ord/2019ord010-e.pdf",
            "ordinance_gazette_content_url_chi": "https://www.legco.gov.hk/yr19-20/chinese/ord/2019ord010-c.pdf",
            "legco_brief_file_reference": "AW-275-010-010-005",
            "legco_brief_url_eng": "http://library.legco.gov.hk:1080/search~S10?/.bills/br/.bills/br/1,1,1,B/l962~bills/br&amp;FF=&amp;1,0,,0,0",
            "legco_brief_url_chi": "http://library.legco.gov.hk:1080/search~S10?/.bills/br/.bills/br/1,1,1,B/l962~bills/br&amp;FF=&amp;1,0,,1,0",
            "first_reading_date": "2019-03-20T00:00:00",
            "first_reading_date_hansard_url_eng": "https://www.legco.gov.hk/yr18-19/english/counmtg/hansard/cm20190320-translate-e.pdf#nameddest=b1r01",
            "first_reading_date_hansard_url_chi": "https://www.legco.gov.hk/yr18-19/chinese/counmtg/hansard/cm20190320-translate-c.pdf#nameddest=b1r01",
            "first_reading_date_2": null,
            "first_reading_date_2_hansard_url_eng": "",
            "first_reading_date_2_hansard_url_chi": "",
            "bills_committee_title_eng": "Bills Committee on Judicial Officers (Extension of Retirement Age) (Amendment) Bill 2019",
            "bills_committee_title_chi": "2019年司法人員(延展退休年齡)(修訂)條例草案委員會",
            "bills_committee_url_eng": "https://www.legco.gov.hk/yr18-19/english/bc/bc101/general/bc101.htm",
            "bills_committee_url_chi": "https://www.legco.gov.hk/yr18-19/chinese/bc/bc101/general/bc101.htm",
            "bills_committee_formation_date": "2019-03-22T00:00:00",
            "bills_committee_report_url_eng": "https://www.legco.gov.hk/yr18-19/english/bc/bc101/reports/bc10120191023cb4-25-e.pdf",
            "bills_committee_report_url_chi": "https://www.legco.gov.hk/yr18-19/chinese/bc/bc101/reports/bc10120191023cb4-25-c.pdf",
            "second_reading_date": "2019-11-06T00:00:00",
            "second_reading_date_hansard_url_eng": "https://www.legco.gov.hk/yr19-20/english/counmtg/hansard/cm20191106-translate-e.pdf#nameddest=b2d01a",
            "second_reading_date_hansard_url_chi": "https://www.legco.gov.hk/yr19-20/chinese/counmtg/hansard/cm20191106-translate-c.pdf#nameddest=b2d01a",
            "second_reading_date_2": "2019-11-07T00:00:00",
            "second_reading_date_2_hansard_url_eng": "https://www.legco.gov.hk/yr19-20/english/counmtg/hansard/cm20191107-translate-e.pdf#nameddest=b2d01a",
            "second_reading_date_2_hansard_url_chi": "https://www.legco.gov.hk/yr19-20/chinese/counmtg/hansard/cm20191107-translate-c.pdf#nameddest=b2d01a",
            "second_reading_date_3": "2019-11-27T00:00:00",
            "second_reading_date_3_hansard_url_eng": "https://www.legco.gov.hk/yr19-20/english/counmtg/hansard/cm20191127-translate-e.pdf#nameddest=cwc01a",
            "second_reading_date_3_hansard_url_chi": "https://www.legco.gov.hk/yr19-20/chinese/counmtg/hansard/cm20191127-translate-c.pdf#nameddest=cwc01a",
            "second_reading_date_4": null,
            "second_reading_date_4_hansard_url_eng": "",
            "second_reading_date_4_hansard_url_chi": "",
            "second_reading_date_5": null,
            "second_reading_date_5_hansard_url_eng": "",
            "second_reading_date_5_hansard_url_chi": "",
            "third_reading_date": "2019-11-27T00:00:00",
            "third_reading_date_hansard_url_eng": "https://www.legco.gov.hk/yr19-20/english/counmtg/hansard/cm20191127-translate-e.pdf#nameddest=b3r01a",
            "third_reading_date_hansard_url_chi": "https://www.legco.gov.hk/yr19-20/chinese/counmtg/hansard/cm20191127-translate-c.pdf#nameddest=b3r01a",
            "additional_information_eng": "",
            "additional_information_chi": "",
            "remarks_eng": "",
            "remarks_chi": ""
        },
        {
            "internal_key": "06673             ",
            "ordinance_title_eng": "Legislative Council Ordinance",
            "ordinance_title_chi": "立法會條例",
            "ordinance_content_url_eng": "https://www.elegislation.gov.hk/hk/cap542?_lang=en",
            "ordinance_content_url_chi": "https://www.elegislation.gov.hk/hk/cap542?_lang=zh-Hant-HK",
            "bill_title_eng": "Electoral Legislation (Miscellaneous Amendments) Bill 2019",
            "bill_title_chi": "2019年選舉法例(雜項修訂)條例草案",
            "proposed_by_eng": "Secretary for Constitutional and Mainland Affairs",
            "proposed_by_chi": "政制及內地事務局局長",
            "bill_gazette_date": "2019-03-01T00:00:00",
            "bill_content_url_eng": "https://www.legco.gov.hk/yr18-19/english/bills/b201903012.pdf",
            "bill_content_url_chi": "https://www.legco.gov.hk/yr18-19/chinese/bills/b201903012.pdf",
            "bill_gazette_date_2": null,
            "bill_content_url_2_eng": "",
            "bill_content_url_2_chi": "",
            "bill_gazette_date_3": null,
            "bill_content_url_3_eng": "",
            "bill_content_url_3_chi": "",
            "ordinance_gazette_date": "2019-12-06T00:00:00",
            "ordinance_year_number_eng": "Ord. No. 11 of 2019",
            "ordinance_year_number_chi": "2019年第11號條例",
            "ordinace_gazette_content_url_eng": "https://www.legco.gov.hk/yr19-20/english/ord/2019ord011-e.pdf",
            "ordinance_gazette_content_url_chi": "https://www.legco.gov.hk/yr19-20/chinese/ord/2019ord011-c.pdf",
            "legco_brief_file_reference": "CMAB C1/30/5/4",
            "legco_brief_url_eng": "http://library.legco.gov.hk:1080/search~S10?/.bills/br/.bills/br/1,1,1,B/l962~bills/br&amp;FF=&amp;1,0,,0,0",
            "legco_brief_url_chi": "http://library.legco.gov.hk:1080/search~S10?/.bills/br/.bills/br/1,1,1,B/l962~bills/br&amp;FF=&amp;1,0,,1,0",
            "first_reading_date": "2019-03-20T00:00:00",
            "first_reading_date_hansard_url_eng": "https://www.legco.gov.hk/yr18-19/english/counmtg/hansard/cm20190320-translate-e.pdf#nameddest=b1r03",
            "first_reading_date_hansard_url_chi": "https://www.legco.gov.hk/yr18-19/chinese/counmtg/hansard/cm20190320-translate-c.pdf#nameddest=b1r03",
            "first_reading_date_2": null,
            "first_reading_date_2_hansard_url_eng": "",
            "first_reading_date_2_hansard_url_chi": "",
            "bills_committee_title_eng": "Bills Committee on Electoral Legislation (Miscellaneous Amendments) Bill 2019",
            "bills_committee_title_chi": "2019年選舉法例(雜項修訂)條例草案委員會",
            "bills_committee_url_eng": "https://www.legco.gov.hk/yr18-19/english/bc/bc55/general/bc55.htm",
            "bills_committee_url_chi": "https://www.legco.gov.hk/yr18-19/chinese/bc/bc55/general/bc55.htm",
            "bills_committee_formation_date": "2019-03-22T00:00:00",
            "bills_committee_report_url_eng": "https://www.legco.gov.hk/yr18-19/english/bc/bc55/reports/bc5520191023cb2-6-e.pdf",
            "bills_committee_report_url_chi": "https://www.legco.gov.hk/yr18-19/chinese/bc/bc55/reports/bc5520191023cb2-6-c.pdf",
            "second_reading_date": "2019-11-27T00:00:00",
            "second_reading_date_hansard_url_eng": "https://www.legco.gov.hk/yr19-20/english/counmtg/hansard/cm20191127-translate-e.pdf#nameddest=b2d01a",
            "second_reading_date_hansard_url_chi": "https://www.legco.gov.hk/yr19-20/chinese/counmtg/hansard/cm20191127-translate-c.pdf#nameddest=b2d01a",
            "second_reading_date_2": "2019-11-28T00:00:00",
            "second_reading_date_2_hansard_url_eng": "https://www.legco.gov.hk/yr19-20/english/counmtg/hansard/cm20191128-translate-e.pdf#nameddest=b2d01a",
            "second_reading_date_2_hansard_url_chi": "https://www.legco.gov.hk/yr19-20/chinese/counmtg/hansard/cm20191128-translate-c.pdf#nameddest=b2d01a",
            "second_reading_date_3": null,
            "second_reading_date_3_hansard_url_eng": "",
            "second_reading_date_3_hansard_url_chi": "",
            "second_reading_date_4": null,
            "second_reading_date_4_hansard_url_eng": "",
            "second_reading_date_4_hansard_url_chi": "",
            "second_reading_date_5": null,
            "second_reading_date_5_hansard_url_eng": "",
            "second_reading_date_5_hansard_url_chi": "",
            "third_reading_date": "2019-11-28T00:00:00",
            "third_reading_date_hansard_url_eng": "https://www.legco.gov.hk/yr19-20/english/counmtg/hansard/cm20191128-translate-e.pdf#nameddest=b3r01a",
            "third_reading_date_hansard_url_chi": "https://www.legco.gov.hk/yr19-20/chinese/counmtg/hansard/cm20191128-translate-c.pdf#nameddest=b3r01a",
            "additional_information_eng": "",
            "additional_information_chi": "",
            "remarks_eng": "",
            "remarks_chi": ""
        },
        {
            "internal_key": "06675             ",
            "ordinance_title_eng": "Inland Revenue Ordinance",
            "ordinance_title_chi": "稅務條例",
            "ordinance_content_url_eng": "https://www.elegislation.gov.hk/hk/cap112?_lang=en",
            "ordinance_content_url_chi": "https://www.elegislation.gov.hk/hk/cap112?_lang=zh-Hant-HK",
            "bill_title_eng": "Inland Revenue (Amendment) (Tax Concessions) Bill 2019",
            "bill_title_chi": "2019年稅務(修訂)(稅務寬免)條例草案",
            "proposed_by_eng": "Secretary for Financial Services and the Treasury",
            "proposed_by_chi": "財經事務及庫務局局長",
            "bill_gazette_date": "2019-03-08T00:00:00",
            "bill_content_url_eng": "https://www.legco.gov.hk/yr18-19/english/bills/b201903081.pdf",
            "bill_content_url_chi": "https://www.legco.gov.hk/yr18-19/chinese/bills/b201903081.pdf",
            "bill_gazette_date_2": null,
            "bill_content_url_2_eng": "",
            "bill_content_url_2_chi": "",
            "bill_gazette_date_3": null,
            "bill_content_url_3_eng": "",
            "bill_content_url_3_chi": "",
            "ordinance_gazette_date": "2019-11-15T00:00:00",
            "ordinance_year_number_eng": "Ord. No. 9 of 2019",
            "ordinance_year_number_chi": "2019年第9號條例",
            "ordinace_gazette_content_url_eng": "https://www.legco.gov.hk/yr19-20/english/ord/2019ord009-e.pdf",
            "ordinance_gazette_content_url_chi": "https://www.legco.gov.hk/yr19-20/chinese/ord/2019ord009-c.pdf",
            "legco_brief_file_reference": "TsyB R 183/535-1/5/0 (19-20) (C)",
            "legco_brief_url_eng": "http://library.legco.gov.hk:1080/search~S10?/.bills/br/.bills/br/1,1,1,B/l962~bills/br&amp;FF=&amp;1,0,,0,0",
            "legco_brief_url_chi": "http://library.legco.gov.hk:1080/search~S10?/.bills/br/.bills/br/1,1,1,B/l962~bills/br&amp;FF=&amp;1,0,,1,0",
            "first_reading_date": "2019-03-20T00:00:00",
            "first_reading_date_hansard_url_eng": "https://www.legco.gov.hk/yr18-19/english/counmtg/hansard/cm20190320-translate-e.pdf#nameddest=b1r02",
            "first_reading_date_hansard_url_chi": "https://www.legco.gov.hk/yr18-19/chinese/counmtg/hansard/cm20190320-translate-c.pdf#nameddest=b1r02",
            "first_reading_date_2": null,
            "first_reading_date_2_hansard_url_eng": "",
            "first_reading_date_2_hansard_url_chi": "",
            "bills_committee_title_eng": "Bills Committee on Inland Revenue (Amendment) (Tax Concessions) Bill 2019",
            "bills_committee_title_chi": "2019年稅務(修訂)(稅務寬免)條例草案委員會",
            "bills_committee_url_eng": "https://www.legco.gov.hk/yr18-19/english/bc/bc08/general/bc08.htm",
            "bills_committee_url_chi": "https://www.legco.gov.hk/yr18-19/chinese/bc/bc08/general/bc08.htm",
            "bills_committee_formation_date": "2019-03-22T00:00:00",
            "bills_committee_report_url_eng": "https://www.legco.gov.hk/yr18-19/english/bc/bc08/reports/bc0820190626cb1-1180-e.pdf",
            "bills_committee_report_url_chi": "https://www.legco.gov.hk/yr18-19/chinese/bc/bc08/reports/bc0820190626cb1-1180-c.pdf",
            "second_reading_date": "2019-10-23T00:00:00",
            "second_reading_date_hansard_url_eng": "https://www.legco.gov.hk/yr19-20/english/counmtg/hansard/cm20191023-translate-e.pdf#nameddest=b2d01a",
            "second_reading_date_hansard_url_chi": "https://www.legco.gov.hk/yr19-20/chinese/counmtg/hansard/cm20191023-translate-c.pdf#nameddest=b2d01a",
            "second_reading_date_2": "2019-10-24T00:00:00",
            "second_reading_date_2_hansard_url_eng": "https://www.legco.gov.hk/yr19-20/english/counmtg/hansard/cm20191024-translate-e.pdf#nameddest=b2d01a",
            "second_reading_date_2_hansard_url_chi": "https://www.legco.gov.hk/yr19-20/chinese/counmtg/hansard/cm20191024-translate-c.pdf#nameddest=b2d01a",
            "second_reading_date_3": "2019-10-30T00:00:00",
            "second_reading_date_3_hansard_url_eng": "https://www.legco.gov.hk/yr19-20/english/counmtg/hansard/cm20191030-translate-e.pdf#nameddest=cwc01a",
            "second_reading_date_3_hansard_url_chi": "https://www.legco.gov.hk/yr19-20/chinese/counmtg/hansard/cm20191030-translate-c.pdf#nameddest=cwc01a",
            "second_reading_date_4": "2019-10-31T00:00:00",
            "second_reading_date_4_hansard_url_eng": "https://www.legco.gov.hk/yr19-20/english/counmtg/hansard/cm20191031-translate-e.pdf#nameddest=cwc01a",
            "second_reading_date_4_hansard_url_chi": "https://www.legco.gov.hk/yr19-20/chinese/counmtg/hansard/cm20191031-translate-c.pdf#nameddest=cwc01a",
            "second_reading_date_5": "2019-11-06T00:00:00",
            "second_reading_date_5_hansard_url_eng": "https://www.legco.gov.hk/yr19-20/english/counmtg/hansard/cm20191106-translate-e.pdf#nameddest=cwc01a",
            "second_reading_date_5_hansard_url_chi": "https://www.legco.gov.hk/yr19-20/chinese/counmtg/hansard/cm20191106-translate-c.pdf#nameddest=cwc01a",
            "third_reading_date": "2019-11-06T00:00:00",
            "third_reading_date_hansard_url_eng": "https://www.legco.gov.hk/yr19-20/english/counmtg/hansard/cm20191106-translate-e.pdf#nameddest=b3r01a",
            "third_reading_date_hansard_url_chi": "https://www.legco.gov.hk/yr19-20/chinese/counmtg/hansard/cm20191106-translate-c.pdf#nameddest=b3r01a",
            "additional_information_eng": "Second Report of the Bills Committee on Inland Revenue (Amendment) (Tax Concessions) Bill 2019\r\n<a href=\"https://www.legco.gov.hk/yr18-19/english/bc/bc08/reports/bc0820191023cb1-10-e.pdf\"> https://www.legco.gov.hk/yr18-19/english/bc/bc08/reports/bc0820191023cb1-10-e.pdf<\/a>",
            "additional_information_chi": "2019年稅務(修訂)(稅務寬免)條例草案委員會第二份報告\r\n<a href=\"https://www.legco.gov.hk/yr18-19/chinese/bc/bc08/reports/bc0820191023cb1-10-c.pdf\"> https://www.legco.gov.hk/yr18-19/chinese/bc/bc08/reports/bc0820191023cb1-10-c.pdf<\/a>",
            "remarks_eng": "",
            "remarks_chi": ""
        }
    ]
}
